{
"meta":{"test_sets":[],"test_metrics":[],"learn_metrics":[{"best_value":"Min","name":"RMSE"}],"launch_mode":"Train","parameters":"","iteration_count":1000,"learn_sets":["learn"],"name":"experiment"},
"iterations":[
{"learn":[5626.473008],"iteration":0,"passed_time":0.000858447141,"remaining_time":0.8575886938},
{"learn":[5370.971668],"iteration":1,"passed_time":0.00164694893,"remaining_time":0.8218275158},
{"learn":[5087.333197],"iteration":2,"passed_time":0.002282936215,"remaining_time":0.7586958021},
{"learn":[4881.620794],"iteration":3,"passed_time":0.002856602331,"remaining_time":0.7112939804},
{"learn":[4680.073606],"iteration":4,"passed_time":0.003573120151,"remaining_time":0.7110509101},
{"learn":[4436.745946],"iteration":5,"passed_time":0.004313782153,"remaining_time":0.71464991},
{"learn":[4237.912718],"iteration":6,"passed_time":0.005213181843,"remaining_time":0.7395270815},
{"learn":[4073.387097],"iteration":7,"passed_time":0.005827165694,"remaining_time":0.7225685461},
{"learn":[3894.553115],"iteration":8,"passed_time":0.006399797283,"remaining_time":0.7046887897},
{"learn":[3727.49213],"iteration":9,"passed_time":0.006975562893,"remaining_time":0.6905807264},
{"learn":[3557.658278],"iteration":10,"passed_time":0.007535786159,"remaining_time":0.6775356829},
{"learn":[3433.443113],"iteration":11,"passed_time":0.007884981439,"remaining_time":0.6491968052},
{"learn":[3288.10599],"iteration":12,"passed_time":0.008516209818,"remaining_time":0.6465768531},
{"learn":[3166.711086],"iteration":13,"passed_time":0.009128715772,"remaining_time":0.6429224108},
{"learn":[3086.59973],"iteration":14,"passed_time":0.009834575516,"remaining_time":0.6458037922},
{"learn":[2979.222601],"iteration":15,"passed_time":0.01041687591,"remaining_time":0.6406378686},
{"learn":[2927.713723],"iteration":16,"passed_time":0.01068316681,"remaining_time":0.6177384103},
{"learn":[2838.272925],"iteration":17,"passed_time":0.01132340235,"remaining_time":0.6177545058},
{"learn":[2723.628126],"iteration":18,"passed_time":0.01192928741,"remaining_time":0.6159279445},
{"learn":[2639.654348],"iteration":19,"passed_time":0.01253565989,"remaining_time":0.6142473346},
{"learn":[2574.483859],"iteration":20,"passed_time":0.01314046917,"remaining_time":0.6125961579},
{"learn":[2505.016815],"iteration":21,"passed_time":0.01379882516,"remaining_time":0.6134205001},
{"learn":[2432.04776],"iteration":22,"passed_time":0.01450129415,"remaining_time":0.6159897558},
{"learn":[2365.047539],"iteration":23,"passed_time":0.01502757266,"remaining_time":0.6111212881},
{"learn":[2331.821099],"iteration":24,"passed_time":0.01526840569,"remaining_time":0.5954678219},
{"learn":[2289.5242],"iteration":25,"passed_time":0.01584309913,"remaining_time":0.5935068672},
{"learn":[2261.509289],"iteration":26,"passed_time":0.01644454529,"remaining_time":0.5926126876},
{"learn":[2210.165183],"iteration":27,"passed_time":0.0171111767,"remaining_time":0.5940022767},
{"learn":[2180.558919],"iteration":28,"passed_time":0.01780908944,"remaining_time":0.596297443},
{"learn":[2152.562605],"iteration":29,"passed_time":0.01840826349,"remaining_time":0.5952005195},
{"learn":[2078.513543],"iteration":30,"passed_time":0.01912306871,"remaining_time":0.5977501155},
{"learn":[2011.562904],"iteration":31,"passed_time":0.01982087332,"remaining_time":0.5995814179},
{"learn":[1990.080588],"iteration":32,"passed_time":0.0204665959,"remaining_time":0.5997332798},
{"learn":[1945.121101],"iteration":33,"passed_time":0.02112108492,"remaining_time":0.6000872952},
{"learn":[1911.398998],"iteration":34,"passed_time":0.02178506052,"remaining_time":0.6006452401},
{"learn":[1863.620421],"iteration":35,"passed_time":0.02247063464,"remaining_time":0.6017136608},
{"learn":[1841.130727],"iteration":36,"passed_time":0.02316201821,"remaining_time":0.6028384738},
{"learn":[1810.825805],"iteration":37,"passed_time":0.02385647532,"remaining_time":0.6039455067},
{"learn":[1782.41037],"iteration":38,"passed_time":0.02444227701,"remaining_time":0.6022827744},
{"learn":[1740.029599],"iteration":39,"passed_time":0.02512719908,"remaining_time":0.603052778},
{"learn":[1710.151364],"iteration":40,"passed_time":0.02581409609,"remaining_time":0.6037980038},
{"learn":[1670.386355],"iteration":41,"passed_time":0.02646277527,"remaining_time":0.6036033025},
{"learn":[1640.082376],"iteration":42,"passed_time":0.02713796806,"remaining_time":0.6039775682},
{"learn":[1603.858025],"iteration":43,"passed_time":0.02780678347,"remaining_time":0.6041655681},
{"learn":[1581.443569],"iteration":44,"passed_time":0.02841270818,"remaining_time":0.6029808069},
{"learn":[1565.715263],"iteration":45,"passed_time":0.02884256977,"remaining_time":0.5981698165},
{"learn":[1539.88238],"iteration":46,"passed_time":0.02956618069,"remaining_time":0.5995014935},
{"learn":[1518.088616],"iteration":47,"passed_time":0.03024471137,"remaining_time":0.5998534421},
{"learn":[1499.629715],"iteration":48,"passed_time":0.0309602287,"remaining_time":0.6008811734},
{"learn":[1467.793645],"iteration":49,"passed_time":0.03163950273,"remaining_time":0.6011505519},
{"learn":[1443.99664],"iteration":50,"passed_time":0.0322690842,"remaining_time":0.6004580569},
{"learn":[1415.598307],"iteration":51,"passed_time":0.03295604729,"remaining_time":0.600814093},
{"learn":[1390.038606],"iteration":52,"passed_time":0.03358800581,"remaining_time":0.6001479529},
{"learn":[1376.882114],"iteration":53,"passed_time":0.03419713703,"remaining_time":0.5990831784},
{"learn":[1353.736312],"iteration":54,"passed_time":0.03488708115,"remaining_time":0.5994234853},
{"learn":[1336.107761],"iteration":55,"passed_time":0.03558496587,"remaining_time":0.5998608532},
{"learn":[1315.972251],"iteration":56,"passed_time":0.03623284922,"remaining_time":0.5994311721},
{"learn":[1286.767317],"iteration":57,"passed_time":0.03690916665,"remaining_time":0.5994557756},
{"learn":[1268.435582],"iteration":58,"passed_time":0.0376125368,"remaining_time":0.5998880869},
{"learn":[1246.02324],"iteration":59,"passed_time":0.03827784411,"remaining_time":0.5996862244},
{"learn":[1219.484758],"iteration":60,"passed_time":0.03896598632,"remaining_time":0.5998206746},
{"learn":[1197.950162],"iteration":61,"passed_time":0.03952804754,"remaining_time":0.5980211064},
{"learn":[1174.87719],"iteration":62,"passed_time":0.04014735462,"remaining_time":0.5971122426},
{"learn":[1153.019515],"iteration":63,"passed_time":0.04079131895,"remaining_time":0.5965730396},
{"learn":[1147.868128],"iteration":64,"passed_time":0.04142457192,"remaining_time":0.5958765346},
{"learn":[1131.821339],"iteration":65,"passed_time":0.04217481302,"remaining_time":0.5968375054},
{"learn":[1117.349325],"iteration":66,"passed_time":0.04290888296,"remaining_time":0.597522206},
{"learn":[1109.371365],"iteration":67,"passed_time":0.04359290668,"remaining_time":0.5974792504},
{"learn":[1100.482053],"iteration":68,"passed_time":0.0442957081,"remaining_time":0.597671076},
{"learn":[1086.962502],"iteration":69,"passed_time":0.04495563771,"remaining_time":0.5972677582},
{"learn":[1071.1476],"iteration":70,"passed_time":0.04557032086,"remaining_time":0.5962651842},
{"learn":[1055.17801],"iteration":71,"passed_time":0.0462110246,"remaining_time":0.5956087615},
{"learn":[1034.74271],"iteration":72,"passed_time":0.04681457987,"remaining_time":0.5944810347},
{"learn":[1020.311645],"iteration":73,"passed_time":0.04737796799,"remaining_time":0.5928648427},
{"learn":[1011.334139],"iteration":74,"passed_time":0.04803327887,"remaining_time":0.5924104394},
{"learn":[993.6517223],"iteration":75,"passed_time":0.04873730627,"remaining_time":0.5925430393},
{"learn":[985.5358431],"iteration":76,"passed_time":0.04947302392,"remaining_time":0.5930337803},
{"learn":[972.6708202],"iteration":77,"passed_time":0.05016025296,"remaining_time":0.5929199132},
{"learn":[959.8364542],"iteration":78,"passed_time":0.05087154407,"remaining_time":0.5930720518},
{"learn":[950.0699902],"iteration":79,"passed_time":0.05163666506,"remaining_time":0.5938216482},
{"learn":[947.1107129],"iteration":80,"passed_time":0.05231073241,"remaining_time":0.5935007788},
{"learn":[934.384285],"iteration":81,"passed_time":0.0529750096,"remaining_time":0.5930616928},
{"learn":[921.1665218],"iteration":82,"passed_time":0.05366491367,"remaining_time":0.5929003112},
{"learn":[912.4245593],"iteration":83,"passed_time":0.05432619861,"remaining_time":0.5924142611},
{"learn":[902.0963194],"iteration":84,"passed_time":0.0550653695,"remaining_time":0.592762507},
{"learn":[891.9890697],"iteration":85,"passed_time":0.0557129805,"remaining_time":0.5921123742},
{"learn":[877.5525117],"iteration":86,"passed_time":0.05647909196,"remaining_time":0.5927058731},
{"learn":[863.9418584],"iteration":87,"passed_time":0.05733731241,"remaining_time":0.5942230559},
{"learn":[857.8081612],"iteration":88,"passed_time":0.05795033543,"remaining_time":0.5931770289},
{"learn":[847.8029809],"iteration":89,"passed_time":0.05869038905,"remaining_time":0.5934250448},
{"learn":[839.678425],"iteration":90,"passed_time":0.05932282538,"remaining_time":0.5925763546},
{"learn":[832.3837162],"iteration":91,"passed_time":0.05992804999,"remaining_time":0.5914637977},
{"learn":[818.411752],"iteration":92,"passed_time":0.06059720704,"remaining_time":0.5909856643},
{"learn":[808.3590331],"iteration":93,"passed_time":0.06137366057,"remaining_time":0.591537622},
{"learn":[798.3056825],"iteration":94,"passed_time":0.06202483213,"remaining_time":0.5908681377},
{"learn":[789.1048316],"iteration":95,"passed_time":0.06272422238,"remaining_time":0.5906530941},
{"learn":[778.5433591],"iteration":96,"passed_time":0.06345108467,"remaining_time":0.5906838088},
{"learn":[768.3179266],"iteration":97,"passed_time":0.06429531717,"remaining_time":0.5917793479},
{"learn":[763.0170356],"iteration":98,"passed_time":0.0649339851,"remaining_time":0.5909648543},
{"learn":[757.3976124],"iteration":99,"passed_time":0.06554782356,"remaining_time":0.5899304121},
{"learn":[745.7866921],"iteration":100,"passed_time":0.06621353659,"remaining_time":0.5893660336},
{"learn":[737.2606394],"iteration":101,"passed_time":0.06683178191,"remaining_time":0.5883817662},
{"learn":[731.1900778],"iteration":102,"passed_time":0.06746975895,"remaining_time":0.5875764444},
{"learn":[726.32349],"iteration":103,"passed_time":0.06817175453,"remaining_time":0.5873258852},
{"learn":[721.0120629],"iteration":104,"passed_time":0.06892395935,"remaining_time":0.5874947011},
{"learn":[712.9859412],"iteration":105,"passed_time":0.06960343524,"remaining_time":0.5870327462},
{"learn":[708.6383217],"iteration":106,"passed_time":0.07040502302,"remaining_time":0.5875858463},
{"learn":[702.6152197],"iteration":107,"passed_time":0.07099037613,"remaining_time":0.5863279214},
{"learn":[695.7918344],"iteration":108,"passed_time":0.07166082203,"remaining_time":0.5857779122},
{"learn":[686.1226027],"iteration":109,"passed_time":0.07226278606,"remaining_time":0.5846716327},
{"learn":[683.3380473],"iteration":110,"passed_time":0.0728596199,"remaining_time":0.5835333522},
{"learn":[679.5259777],"iteration":111,"passed_time":0.07353048554,"remaining_time":0.5829917068},
{"learn":[675.3999086],"iteration":112,"passed_time":0.07428546912,"remaining_time":0.5831080629},
{"learn":[671.1947717],"iteration":113,"passed_time":0.07486944126,"remaining_time":0.5818800435},
{"learn":[666.0871968],"iteration":114,"passed_time":0.07558946118,"remaining_time":0.5817102012},
{"learn":[661.9103451],"iteration":115,"passed_time":0.07638334026,"remaining_time":0.582093731},
{"learn":[658.1772814],"iteration":116,"passed_time":0.07704177756,"remaining_time":0.5814349537},
{"learn":[649.4188864],"iteration":117,"passed_time":0.07770127421,"remaining_time":0.5807841004},
{"learn":[645.3771992],"iteration":118,"passed_time":0.07838590511,"remaining_time":0.5803191799},
{"learn":[641.6880138],"iteration":119,"passed_time":0.07909521969,"remaining_time":0.5800316111},
{"learn":[634.8691141],"iteration":120,"passed_time":0.07969348177,"remaining_time":0.5789303345},
{"learn":[627.2464083],"iteration":121,"passed_time":0.08033209002,"remaining_time":0.5781276642},
{"learn":[624.809354],"iteration":122,"passed_time":0.08105561122,"remaining_time":0.5779330979},
{"learn":[617.5838101],"iteration":123,"passed_time":0.08184069743,"remaining_time":0.578164927},
{"learn":[614.8341231],"iteration":124,"passed_time":0.08255745315,"remaining_time":0.5779021721},
{"learn":[608.4454038],"iteration":125,"passed_time":0.0833544174,"remaining_time":0.5781885778},
{"learn":[607.6085113],"iteration":126,"passed_time":0.08394063442,"remaining_time":0.5770092429},
{"learn":[603.3403057],"iteration":127,"passed_time":0.08461806529,"remaining_time":0.5764605698},
{"learn":[595.8926438],"iteration":128,"passed_time":0.08526310979,"remaining_time":0.5756912297},
{"learn":[594.583243],"iteration":129,"passed_time":0.08585488234,"remaining_time":0.5745672895},
{"learn":[589.8812441],"iteration":130,"passed_time":0.08659040135,"remaining_time":0.5744050288},
{"learn":[584.4275443],"iteration":131,"passed_time":0.08731767497,"remaining_time":0.5741798627},
{"learn":[580.8384155],"iteration":132,"passed_time":0.08798239432,"remaining_time":0.5735393675},
{"learn":[576.4940793],"iteration":133,"passed_time":0.08867515085,"remaining_time":0.5730797063},
{"learn":[572.4155562],"iteration":134,"passed_time":0.08938232268,"remaining_time":0.5727089564},
{"learn":[567.2672089],"iteration":135,"passed_time":0.0900855879,"remaining_time":0.5723084407},
{"learn":[564.3946575],"iteration":136,"passed_time":0.09082917325,"remaining_time":0.5721574928},
{"learn":[561.5402208],"iteration":137,"passed_time":0.09156918842,"remaining_time":0.5719756552},
{"learn":[558.3530825],"iteration":138,"passed_time":0.09234679303,"remaining_time":0.5720186244},
{"learn":[553.8203017],"iteration":139,"passed_time":0.09298250716,"remaining_time":0.5711782583},
{"learn":[549.7989043],"iteration":140,"passed_time":0.09369834931,"remaining_time":0.5708289508},
{"learn":[544.0047996],"iteration":141,"passed_time":0.0943895887,"remaining_time":0.5703258247},
{"learn":[538.5549022],"iteration":142,"passed_time":0.09511774225,"remaining_time":0.5700412944},
{"learn":[533.3177735],"iteration":143,"passed_time":0.09586144695,"remaining_time":0.5698430458},
{"learn":[529.7436296],"iteration":144,"passed_time":0.09648690913,"remaining_time":0.5689400504},
{"learn":[528.1253937],"iteration":145,"passed_time":0.09713929706,"remaining_time":0.5681983541},
{"learn":[524.3292865],"iteration":146,"passed_time":0.09788722479,"remaining_time":0.5680122636},
{"learn":[521.5013394],"iteration":147,"passed_time":0.09850683266,"remaining_time":0.5670798745},
{"learn":[519.0393602],"iteration":148,"passed_time":0.09928870273,"remaining_time":0.5670784297},
{"learn":[515.3790561],"iteration":149,"passed_time":0.09996827234,"remaining_time":0.5664868766},
{"learn":[512.2388396],"iteration":150,"passed_time":0.1006644513,"remaining_time":0.5659875439},
{"learn":[508.9911513],"iteration":151,"passed_time":0.1013742933,"remaining_time":0.5655618469},
{"learn":[507.1944657],"iteration":152,"passed_time":0.10209706,"remaining_time":0.5652039855},
{"learn":[502.3877188],"iteration":153,"passed_time":0.1027629128,"remaining_time":0.5645287286},
{"learn":[497.5611049],"iteration":154,"passed_time":0.1034207521,"remaining_time":0.5638099066},
{"learn":[495.0678598],"iteration":155,"passed_time":0.1040047274,"remaining_time":0.5626922433},
{"learn":[490.9456247],"iteration":156,"passed_time":0.1046451752,"remaining_time":0.5618846034},
{"learn":[485.5725384],"iteration":157,"passed_time":0.1053261647,"remaining_time":0.5612951307},
{"learn":[481.8089432],"iteration":158,"passed_time":0.1059983624,"remaining_time":0.560658005},
{"learn":[479.5022662],"iteration":159,"passed_time":0.1067695156,"remaining_time":0.5605399567},
{"learn":[475.5177308],"iteration":160,"passed_time":0.107461928,"remaining_time":0.5600034635},
{"learn":[474.3685386],"iteration":161,"passed_time":0.1082033755,"remaining_time":0.5597186952},
{"learn":[471.5848541],"iteration":162,"passed_time":0.1089141771,"remaining_time":0.5592709587},
{"learn":[469.2765654],"iteration":163,"passed_time":0.1095522727,"remaining_time":0.5584493902},
{"learn":[466.1708346],"iteration":164,"passed_time":0.1102067429,"remaining_time":0.5577129112},
{"learn":[464.1611727],"iteration":165,"passed_time":0.1108752636,"remaining_time":0.5570480109},
{"learn":[461.5567348],"iteration":166,"passed_time":0.1114819332,"remaining_time":0.5560745532},
{"learn":[458.7453414],"iteration":167,"passed_time":0.1121061582,"remaining_time":0.5551924026},
{"learn":[456.202386],"iteration":168,"passed_time":0.1127637849,"remaining_time":0.5544775457},
{"learn":[454.3373781],"iteration":169,"passed_time":0.1135012103,"remaining_time":0.554152968},
{"learn":[451.4324692],"iteration":170,"passed_time":0.1142429521,"remaining_time":0.5538444871},
{"learn":[447.1706926],"iteration":171,"passed_time":0.1149145623,"remaining_time":0.5531933581},
{"learn":[443.9854056],"iteration":172,"passed_time":0.1155290412,"remaining_time":0.5522688848},
{"learn":[441.4219157],"iteration":173,"passed_time":0.116162772,"remaining_time":0.5514393658},
{"learn":[437.7512595],"iteration":174,"passed_time":0.116817287,"remaining_time":0.5507100675},
{"learn":[436.6888208],"iteration":175,"passed_time":0.1174933317,"remaining_time":0.5500824167},
{"learn":[434.0769012],"iteration":176,"passed_time":0.1181842799,"remaining_time":0.5495235163},
{"learn":[432.0398938],"iteration":177,"passed_time":0.118831613,"remaining_time":0.5487617184},
{"learn":[430.2324037],"iteration":178,"passed_time":0.1195220329,"remaining_time":0.5481988213},
{"learn":[426.9125643],"iteration":179,"passed_time":0.1204315452,"remaining_time":0.5486325947},
{"learn":[423.0630426],"iteration":180,"passed_time":0.1211742266,"remaining_time":0.5482966385},
{"learn":[420.8531312],"iteration":181,"passed_time":0.121885625,"remaining_time":0.5478156114},
{"learn":[420.1063381],"iteration":182,"passed_time":0.1225074533,"remaining_time":0.5469321824},
{"learn":[418.2454789],"iteration":183,"passed_time":0.1231234686,"remaining_time":0.5460258172},
{"learn":[416.0476912],"iteration":184,"passed_time":0.1237806495,"remaining_time":0.5453039423},
{"learn":[412.8349173],"iteration":185,"passed_time":0.1244017629,"remaining_time":0.5444249192},
{"learn":[410.4325631],"iteration":186,"passed_time":0.125205046,"remaining_time":0.5443406547},
{"learn":[407.764091],"iteration":187,"passed_time":0.1258764764,"remaining_time":0.5436792491},
{"learn":[407.6163677],"iteration":188,"passed_time":0.1265344515,"remaining_time":0.5429600009},
{"learn":[405.3469265],"iteration":189,"passed_time":0.1273909257,"remaining_time":0.5430876306},
{"learn":[404.2236586],"iteration":190,"passed_time":0.1280076483,"remaining_time":0.5421894631},
{"learn":[402.1499373],"iteration":191,"passed_time":0.1286274636,"remaining_time":0.5413072427},
{"learn":[399.8793719],"iteration":192,"passed_time":0.1293474739,"remaining_time":0.5408466914},
{"learn":[397.8399059],"iteration":193,"passed_time":0.1299750432,"remaining_time":0.5399994062},
{"learn":[395.0433927],"iteration":194,"passed_time":0.1306227856,"remaining_time":0.5392376532},
{"learn":[393.7594528],"iteration":195,"passed_time":0.1313116895,"remaining_time":0.5386459102},
{"learn":[390.9567471],"iteration":196,"passed_time":0.1320038145,"remaining_time":0.5380663097},
{"learn":[388.541301],"iteration":197,"passed_time":0.1326850959,"remaining_time":0.537441651},
{"learn":[385.1016275],"iteration":198,"passed_time":0.1333782381,"remaining_time":0.5368641644},
{"learn":[383.1807303],"iteration":199,"passed_time":0.1340924974,"remaining_time":0.5363699897},
{"learn":[381.7308926],"iteration":200,"passed_time":0.1348127801,"remaining_time":0.5358975685},
{"learn":[380.3442417],"iteration":201,"passed_time":0.1355595343,"remaining_time":0.5355272691},
{"learn":[378.7951922],"iteration":202,"passed_time":0.1362488047,"remaining_time":0.5349275733},
{"learn":[377.2094917],"iteration":203,"passed_time":0.1369105487,"remaining_time":0.5342195919},
{"learn":[375.2431918],"iteration":204,"passed_time":0.1375470402,"remaining_time":0.5334141316},
{"learn":[374.3600262],"iteration":205,"passed_time":0.1381894373,"remaining_time":0.532633074},
{"learn":[373.6446637],"iteration":206,"passed_time":0.1388487573,"remaining_time":0.5319181864},
{"learn":[370.0923384],"iteration":207,"passed_time":0.1395454197,"remaining_time":0.5313460211},
{"learn":[366.8947664],"iteration":208,"passed_time":0.1403637714,"remaining_time":0.5312332209},
{"learn":[362.9903812],"iteration":209,"passed_time":0.1410042588,"remaining_time":0.5304445928},
{"learn":[360.2830097],"iteration":210,"passed_time":0.1416574262,"remaining_time":0.5297047832},
{"learn":[358.3339774],"iteration":211,"passed_time":0.1422957649,"remaining_time":0.5289106732},
{"learn":[356.6086751],"iteration":212,"passed_time":0.1429239233,"remaining_time":0.5280804115},
{"learn":[355.4840584],"iteration":213,"passed_time":0.1435776169,"remaining_time":0.5273458266},
{"learn":[355.0961098],"iteration":214,"passed_time":0.1442420271,"remaining_time":0.5266511221},
{"learn":[354.4365278],"iteration":215,"passed_time":0.1449407032,"remaining_time":0.5260810709},
{"learn":[353.704928],"iteration":216,"passed_time":0.14561531,"remaining_time":0.5254229851},
{"learn":[351.2027167],"iteration":217,"passed_time":0.1463537604,"remaining_time":0.5249937644},
{"learn":[349.2858944],"iteration":218,"passed_time":0.1470177965,"remaining_time":0.5242963427},
{"learn":[348.3477699],"iteration":219,"passed_time":0.1477783652,"remaining_time":0.5239414767},
{"learn":[346.6336859],"iteration":220,"passed_time":0.1484673822,"remaining_time":0.5233307272},
{"learn":[346.0004169],"iteration":221,"passed_time":0.1491370987,"remaining_time":0.5226516343},
{"learn":[344.085031],"iteration":222,"passed_time":0.1497755924,"remaining_time":0.5218638355},
{"learn":[343.1310349],"iteration":223,"passed_time":0.1503786899,"remaining_time":0.5209547472},
{"learn":[342.1349436],"iteration":224,"passed_time":0.1510748152,"remaining_time":0.5203688078},
{"learn":[340.7310265],"iteration":225,"passed_time":0.1517654638,"remaining_time":0.519763137},
{"learn":[338.9473213],"iteration":226,"passed_time":0.1524124384,"remaining_time":0.519007995},
{"learn":[337.7746767],"iteration":227,"passed_time":0.1531170009,"remaining_time":0.5184487924},
{"learn":[336.8585241],"iteration":228,"passed_time":0.1538221845,"remaining_time":0.5178904117},
{"learn":[335.4213986],"iteration":229,"passed_time":0.1544732059,"remaining_time":0.5171494285},
{"learn":[332.9837229],"iteration":230,"passed_time":0.1551437804,"remaining_time":0.5164743165},
{"learn":[330.5085861],"iteration":231,"passed_time":0.1557107679,"remaining_time":0.5154563352},
{"learn":[329.9461272],"iteration":232,"passed_time":0.1563188494,"remaining_time":0.5145774999},
{"learn":[327.8746443],"iteration":233,"passed_time":0.1570609885,"remaining_time":0.514139817},
{"learn":[327.2265177],"iteration":234,"passed_time":0.1577903788,"remaining_time":0.5136580417},
{"learn":[325.6654704],"iteration":235,"passed_time":0.158517789,"remaining_time":0.5131677577},
{"learn":[324.8118402],"iteration":236,"passed_time":0.1592938669,"remaining_time":0.5128321537},
{"learn":[323.3413919],"iteration":237,"passed_time":0.1600877364,"remaining_time":0.5125498113},
{"learn":[322.8068895],"iteration":238,"passed_time":0.1607763323,"remaining_time":0.5119279871},
{"learn":[321.6760746],"iteration":239,"passed_time":0.1613866014,"remaining_time":0.5110575712},
{"learn":[321.0753109],"iteration":240,"passed_time":0.1619378259,"remaining_time":0.5100033606},
{"learn":[320.136603],"iteration":241,"passed_time":0.1626077888,"remaining_time":0.5093252229},
{"learn":[318.130956],"iteration":242,"passed_time":0.1632390505,"remaining_time":0.5085265893},
{"learn":[316.9454623],"iteration":243,"passed_time":0.1639530266,"remaining_time":0.507985607},
{"learn":[315.3695361],"iteration":244,"passed_time":0.1647398374,"remaining_time":0.5076676623},
{"learn":[314.6163682],"iteration":245,"passed_time":0.1654496675,"remaining_time":0.5071099564},
{"learn":[314.0863241],"iteration":246,"passed_time":0.1661713595,"remaining_time":0.5065871811},
{"learn":[312.4670658],"iteration":247,"passed_time":0.1668147799,"remaining_time":0.5058254618},
{"learn":[312.3943347],"iteration":248,"passed_time":0.1674257407,"remaining_time":0.5049667923},
{"learn":[310.9983329],"iteration":249,"passed_time":0.1680402428,"remaining_time":0.5041207285},
{"learn":[309.4745305],"iteration":250,"passed_time":0.1686317022,"remaining_time":0.5032077488},
{"learn":[308.7354166],"iteration":251,"passed_time":0.1692207605,"remaining_time":0.5022901937},
{"learn":[308.6679435],"iteration":252,"passed_time":0.1699770024,"remaining_time":0.501868857},
{"learn":[307.4432853],"iteration":253,"passed_time":0.1706255851,"remaining_time":0.5011286869},
{"learn":[305.9291004],"iteration":254,"passed_time":0.171277939,"remaining_time":0.5004002531},
{"learn":[304.7031466],"iteration":255,"passed_time":0.1720261671,"remaining_time":0.4999510481},
{"learn":[303.2066739],"iteration":256,"passed_time":0.172724077,"remaining_time":0.4993540437},
{"learn":[301.7438607],"iteration":257,"passed_time":0.1734210309,"remaining_time":0.4987535076},
{"learn":[300.7639899],"iteration":258,"passed_time":0.1740978002,"remaining_time":0.4980944785},
{"learn":[300.2478545],"iteration":259,"passed_time":0.1746833283,"remaining_time":0.4971756267},
{"learn":[300.1869271],"iteration":260,"passed_time":0.1752263575,"remaining_time":0.4961389969},
{"learn":[298.0376289],"iteration":261,"passed_time":0.1758029774,"remaining_time":0.4952007532},
{"learn":[295.7322507],"iteration":262,"passed_time":0.1765978233,"remaining_time":0.4948767901},
{"learn":[295.6688039],"iteration":263,"passed_time":0.1773195462,"remaining_time":0.4943454016},
{"learn":[293.7678168],"iteration":264,"passed_time":0.1780902828,"remaining_time":0.4939485203},
{"learn":[292.210238],"iteration":265,"passed_time":0.1788703422,"remaining_time":0.4935745533},
{"learn":[291.6924453],"iteration":266,"passed_time":0.1795494897,"remaining_time":0.4929205091},
{"learn":[291.3504255],"iteration":267,"passed_time":0.1801424149,"remaining_time":0.492030775},
{"learn":[290.8080486],"iteration":268,"passed_time":0.1807899426,"remaining_time":0.4912916283},
{"learn":[290.4145658],"iteration":269,"passed_time":0.1814891105,"remaining_time":0.4906927803},
{"learn":[289.3042846],"iteration":270,"passed_time":0.1821563647,"remaining_time":0.4900073428},
{"learn":[287.1078888],"iteration":271,"passed_time":0.1828263561,"remaining_time":0.4893293648},
{"learn":[285.7384592],"iteration":272,"passed_time":0.1835612931,"remaining_time":0.488824396},
{"learn":[284.0152962],"iteration":273,"passed_time":0.1842706513,"remaining_time":0.488249974},
{"learn":[282.6440156],"iteration":274,"passed_time":0.1849755839,"remaining_time":0.487662903},
{"learn":[282.0539445],"iteration":275,"passed_time":0.1856660259,"remaining_time":0.4870369664},
{"learn":[280.6499423],"iteration":276,"passed_time":0.1863492578,"remaining_time":0.486391745},
{"learn":[279.9090466],"iteration":277,"passed_time":0.1869904089,"remaining_time":0.4856369612},
{"learn":[278.956268],"iteration":278,"passed_time":0.1876030887,"remaining_time":0.4848094155},
{"learn":[277.4131704],"iteration":279,"passed_time":0.1882714451,"remaining_time":0.4841265731},
{"learn":[276.1968122],"iteration":280,"passed_time":0.1889061848,"remaining_time":0.483357818},
{"learn":[274.4279527],"iteration":281,"passed_time":0.1896129781,"remaining_time":0.4827734691},
{"learn":[272.98828],"iteration":282,"passed_time":0.1903523821,"remaining_time":0.4822708762},
{"learn":[271.1583049],"iteration":283,"passed_time":0.1910564535,"remaining_time":0.4816775378},
{"learn":[269.9461397],"iteration":284,"passed_time":0.1917864362,"remaining_time":0.4811484278},
{"learn":[269.3962621],"iteration":285,"passed_time":0.1924835179,"remaining_time":0.4805357755},
{"learn":[268.8263034],"iteration":286,"passed_time":0.1931745835,"remaining_time":0.4799075889},
{"learn":[268.1092632],"iteration":287,"passed_time":0.1938988004,"remaining_time":0.4793609232},
{"learn":[267.7821563],"iteration":288,"passed_time":0.1944935848,"remaining_time":0.4784945979},
{"learn":[267.0114231],"iteration":289,"passed_time":0.195157576,"remaining_time":0.4777995827},
{"learn":[265.7049423],"iteration":290,"passed_time":0.1958587181,"remaining_time":0.477195296},
{"learn":[265.3823731],"iteration":291,"passed_time":0.1965507809,"remaining_time":0.4765683319},
{"learn":[264.412534],"iteration":292,"passed_time":0.1973226634,"remaining_time":0.4761335257},
{"learn":[263.4181242],"iteration":293,"passed_time":0.198062071,"remaining_time":0.4756184426},
{"learn":[262.5690498],"iteration":294,"passed_time":0.1987332819,"remaining_time":0.4749388601},
{"learn":[261.3118862],"iteration":295,"passed_time":0.1993867392,"remaining_time":0.4742171094},
{"learn":[260.2802212],"iteration":296,"passed_time":0.1999742571,"remaining_time":0.4733397398},
{"learn":[258.9408035],"iteration":297,"passed_time":0.2006981307,"remaining_time":0.4727855295},
{"learn":[258.8351199],"iteration":298,"passed_time":0.2013491433,"remaining_time":0.4720593627},
{"learn":[258.2184398],"iteration":299,"passed_time":0.2019557897,"remaining_time":0.4712301761},
{"learn":[257.6479657],"iteration":300,"passed_time":0.2026914033,"remaining_time":0.4707019631},
{"learn":[257.0816837],"iteration":301,"passed_time":0.2034094254,"remaining_time":0.4701317183},
{"learn":[257.0100655],"iteration":302,"passed_time":0.2040881728,"remaining_time":0.4694701532},
{"learn":[256.5677327],"iteration":303,"passed_time":0.2047283466,"remaining_time":0.468720162},
{"learn":[255.710947],"iteration":304,"passed_time":0.2053976939,"remaining_time":0.4680373681},
{"learn":[254.4141824],"iteration":305,"passed_time":0.2060125909,"remaining_time":0.4672311703},
{"learn":[253.9811694],"iteration":306,"passed_time":0.2066991888,"remaining_time":0.4665880711},
{"learn":[253.1909111],"iteration":307,"passed_time":0.2073284618,"remaining_time":0.4658158948},
{"learn":[253.091541],"iteration":308,"passed_time":0.2079901193,"remaining_time":0.4651170628},
{"learn":[252.1578524],"iteration":309,"passed_time":0.2087647617,"remaining_time":0.4646699534},
{"learn":[251.2914628],"iteration":310,"passed_time":0.209462853,"remaining_time":0.4640511439},
{"learn":[249.4040439],"iteration":311,"passed_time":0.2101867559,"remaining_time":0.4634887439},
{"learn":[247.9813791],"iteration":312,"passed_time":0.2108547707,"remaining_time":0.4628026437},
{"learn":[246.5729476],"iteration":313,"passed_time":0.2115403068,"remaining_time":0.4621549378},
{"learn":[246.5230183],"iteration":314,"passed_time":0.2122666052,"remaining_time":0.4615956334},
{"learn":[245.2652885],"iteration":315,"passed_time":0.2128529956,"remaining_time":0.4607324335},
{"learn":[243.9116573],"iteration":316,"passed_time":0.2134757892,"remaining_time":0.4599494132},
{"learn":[243.1271849],"iteration":317,"passed_time":0.214099292,"remaining_time":0.4591689219},
{"learn":[242.5410299],"iteration":318,"passed_time":0.2146767081,"remaining_time":0.458291029},
{"learn":[241.7087278],"iteration":319,"passed_time":0.2153140792,"remaining_time":0.4575424183},
{"learn":[240.8244887],"iteration":320,"passed_time":0.2160004231,"remaining_time":0.4568980913},
{"learn":[240.0555088],"iteration":321,"passed_time":0.2167360951,"remaining_time":0.456357368},
{"learn":[239.2557298],"iteration":322,"passed_time":0.2174472725,"remaining_time":0.4557640974},
{"learn":[238.4400078],"iteration":323,"passed_time":0.218126893,"remaining_time":0.4551042581},
{"learn":[238.3669479],"iteration":324,"passed_time":0.218730441,"remaining_time":0.4542863006},
{"learn":[237.590491],"iteration":325,"passed_time":0.2194166463,"remaining_time":0.453640551},
{"learn":[237.5141179],"iteration":326,"passed_time":0.2200638752,"remaining_time":0.4529143365},
{"learn":[236.3126708],"iteration":327,"passed_time":0.2207052543,"remaining_time":0.4521766185},
{"learn":[236.2649892],"iteration":328,"passed_time":0.2213801603,"remaining_time":0.4515078649},
{"learn":[235.1389412],"iteration":329,"passed_time":0.222076636,"remaining_time":0.450882867},
{"learn":[234.1336029],"iteration":330,"passed_time":0.222790333,"remaining_time":0.450292244},
{"learn":[233.2914968],"iteration":331,"passed_time":0.223412865,"remaining_time":0.4495174513},
{"learn":[232.5472336],"iteration":332,"passed_time":0.2240177352,"remaining_time":0.4487081962},
{"learn":[231.2069104],"iteration":333,"passed_time":0.2246696625,"remaining_time":0.4479939977},
{"learn":[230.2241811],"iteration":334,"passed_time":0.225352397,"remaining_time":0.4473413253},
{"learn":[228.9871849],"iteration":335,"passed_time":0.2260217002,"remaining_time":0.4466619313},
{"learn":[228.4293431],"iteration":336,"passed_time":0.2267522841,"remaining_time":0.4461031583},
{"learn":[227.9054649],"iteration":337,"passed_time":0.2274747435,"remaining_time":0.4455274562},
{"learn":[226.7805163],"iteration":338,"passed_time":0.2281677335,"remaining_time":0.4448934274},
{"learn":[225.8186079],"iteration":339,"passed_time":0.2288325358,"remaining_time":0.4442043342},
{"learn":[225.1831819],"iteration":340,"passed_time":0.2295016848,"remaining_time":0.4435237839},
{"learn":[224.6830938],"iteration":341,"passed_time":0.2302014704,"remaining_time":0.4429022442},
{"learn":[224.1100126],"iteration":342,"passed_time":0.2308995033,"remaining_time":0.4422768911},
{"learn":[223.7502732],"iteration":343,"passed_time":0.2314890394,"remaining_time":0.4414442146},
{"learn":[222.9937273],"iteration":344,"passed_time":0.2321622012,"remaining_time":0.4407717152},
{"learn":[222.5496818],"iteration":345,"passed_time":0.2328598115,"remaining_time":0.4401454241},
{"learn":[222.2622167],"iteration":346,"passed_time":0.2335889255,"remaining_time":0.4395780068},
{"learn":[221.2466052],"iteration":347,"passed_time":0.2342973261,"remaining_time":0.4389708524},
{"learn":[219.9022218],"iteration":348,"passed_time":0.2350174161,"remaining_time":0.4383849223},
{"learn":[219.4162311],"iteration":349,"passed_time":0.2357921927,"remaining_time":0.4378997864},
{"learn":[218.2636059],"iteration":350,"passed_time":0.2364718925,"remaining_time":0.4372372029},
{"learn":[217.5150167],"iteration":351,"passed_time":0.2371150133,"remaining_time":0.4365071836},
{"learn":[216.8805673],"iteration":352,"passed_time":0.2378067778,"remaining_time":0.4358668136},
{"learn":[216.385464],"iteration":353,"passed_time":0.2384118554,"remaining_time":0.4350679621},
{"learn":[215.663494],"iteration":354,"passed_time":0.2390062417,"remaining_time":0.4342507771},
{"learn":[215.0441425],"iteration":355,"passed_time":0.239731125,"remaining_time":0.4336709116},
{"learn":[214.0319043],"iteration":356,"passed_time":0.2403630928,"remaining_time":0.4329228814},
{"learn":[213.4081896],"iteration":357,"passed_time":0.241139664,"remaining_time":0.4324348165},
{"learn":[213.3238737],"iteration":358,"passed_time":0.241830895,"remaining_time":0.431792768},
{"learn":[212.1563107],"iteration":359,"passed_time":0.2425902562,"remaining_time":0.4312715666},
{"learn":[211.5079309],"iteration":360,"passed_time":0.2433217212,"remaining_time":0.4306996672},
{"learn":[210.6601437],"iteration":361,"passed_time":0.2439474622,"remaining_time":0.4299405548},
{"learn":[210.1219056],"iteration":362,"passed_time":0.2445600702,"remaining_time":0.4291591315},
{"learn":[209.41157],"iteration":363,"passed_time":0.2452463493,"remaining_time":0.4285073575},
{"learn":[208.8291009],"iteration":364,"passed_time":0.2458453747,"remaining_time":0.4277035971},
{"learn":[208.3000319],"iteration":365,"passed_time":0.2464210758,"remaining_time":0.4268605521},
{"learn":[207.6956074],"iteration":366,"passed_time":0.2471257284,"remaining_time":0.426241379},
{"learn":[207.5881192],"iteration":367,"passed_time":0.2479715113,"remaining_time":0.4258641173},
{"learn":[207.258023],"iteration":368,"passed_time":0.2487970366,"remaining_time":0.4254496751},
{"learn":[206.2585124],"iteration":369,"passed_time":0.2494645872,"remaining_time":0.4247640269},
{"learn":[205.9295816],"iteration":370,"passed_time":0.2502009233,"remaining_time":0.4241950963},
{"learn":[204.9459661],"iteration":371,"passed_time":0.2508737606,"remaining_time":0.423518069},
{"learn":[204.2206656],"iteration":372,"passed_time":0.2514702813,"remaining_time":0.4227127784},
{"learn":[203.7089983],"iteration":373,"passed_time":0.2520669197,"remaining_time":0.4219088014},
{"learn":[203.3167678],"iteration":374,"passed_time":0.2527488763,"remaining_time":0.4212481272},
{"learn":[202.6497067],"iteration":375,"passed_time":0.2535017572,"remaining_time":0.4207050439},
{"learn":[201.917535],"iteration":376,"passed_time":0.2542007389,"remaining_time":0.4200717781},
{"learn":[201.7728374],"iteration":377,"passed_time":0.2548623151,"remaining_time":0.4193766137},
{"learn":[201.113343],"iteration":378,"passed_time":0.2555533442,"remaining_time":0.4187298858},
{"learn":[200.2172113],"iteration":379,"passed_time":0.2562359857,"remaining_time":0.4180692399},
{"learn":[199.5688638],"iteration":380,"passed_time":0.2568702412,"remaining_time":0.4173298669},
{"learn":[198.942098],"iteration":381,"passed_time":0.2575191294,"remaining_time":0.4166147172},
{"learn":[198.7574405],"iteration":382,"passed_time":0.2581409089,"remaining_time":0.4158562422},
{"learn":[198.4018047],"iteration":383,"passed_time":0.2587163845,"remaining_time":0.4150242002},
{"learn":[197.8209791],"iteration":384,"passed_time":0.2592996998,"remaining_time":0.414206014},
{"learn":[196.9545814],"iteration":385,"passed_time":0.2598964059,"remaining_time":0.4134103451},
{"learn":[196.5661587],"iteration":386,"passed_time":0.2605249781,"remaining_time":0.4126661797},
{"learn":[195.6023348],"iteration":387,"passed_time":0.261133849,"remaining_time":0.411891535},
{"learn":[194.8627765],"iteration":388,"passed_time":0.2618219203,"remaining_time":0.4112421421},
{"learn":[194.3137002],"iteration":389,"passed_time":0.2625459946,"remaining_time":0.4106488633},
{"learn":[193.4753333],"iteration":390,"passed_time":0.2631445707,"remaining_time":0.4098594464},
{"learn":[193.2005549],"iteration":391,"passed_time":0.2638666965,"remaining_time":0.4092626313},
{"learn":[192.1246228],"iteration":392,"passed_time":0.2644967766,"remaining_time":0.4085230112},
{"learn":[191.4574034],"iteration":393,"passed_time":0.265150783,"remaining_time":0.4078207475},
{"learn":[190.5266707],"iteration":394,"passed_time":0.2657878369,"remaining_time":0.4070927628},
{"learn":[189.4340347],"iteration":395,"passed_time":0.2664890875,"remaining_time":0.4064631536},
{"learn":[189.0736808],"iteration":396,"passed_time":0.2672107507,"remaining_time":0.4058641881},
{"learn":[188.2760713],"iteration":397,"passed_time":0.267942323,"remaining_time":0.4052795942},
{"learn":[187.4768168],"iteration":398,"passed_time":0.268644784,"remaining_time":0.404650414},
{"learn":[186.3570484],"iteration":399,"passed_time":0.2692615551,"remaining_time":0.4038923326},
{"learn":[185.0207341],"iteration":400,"passed_time":0.2698652161,"remaining_time":0.4031153726},
{"learn":[184.4743738],"iteration":401,"passed_time":0.2704822066,"remaining_time":0.4023591033},
{"learn":[183.8551011],"iteration":402,"passed_time":0.2711710857,"remaining_time":0.4017100203},
{"learn":[183.7123263],"iteration":403,"passed_time":0.271819714,"remaining_time":0.4010013603},
{"learn":[183.2398898],"iteration":404,"passed_time":0.2725780527,"remaining_time":0.4004541762},
{"learn":[182.6802276],"iteration":405,"passed_time":0.2732909691,"remaining_time":0.3998394967},
{"learn":[181.7910254],"iteration":406,"passed_time":0.2740011628,"remaining_time":0.3992203674},
{"learn":[181.2891863],"iteration":407,"passed_time":0.2746753928,"remaining_time":0.3985486091},
{"learn":[180.7319944],"iteration":408,"passed_time":0.2753522645,"remaining_time":0.3978806561},
{"learn":[180.3713786],"iteration":409,"passed_time":0.2759467129,"remaining_time":0.3970940503},
{"learn":[179.9743129],"iteration":410,"passed_time":0.276720052,"remaining_time":0.3965647461},
{"learn":[178.9633866],"iteration":411,"passed_time":0.2773568051,"remaining_time":0.3958393238},
{"learn":[178.55726],"iteration":412,"passed_time":0.2780561004,"remaining_time":0.3952032226},
{"learn":[177.833897],"iteration":413,"passed_time":0.2787739199,"remaining_time":0.3945930364},
{"learn":[177.3252677],"iteration":414,"passed_time":0.2794081958,"remaining_time":0.3938645652},
{"learn":[176.6818911],"iteration":415,"passed_time":0.2801724533,"remaining_time":0.393319021},
{"learn":[176.316786],"iteration":416,"passed_time":0.2808458013,"remaining_time":0.3926453289},
{"learn":[175.9326756],"iteration":417,"passed_time":0.2815253177,"remaining_time":0.391980227},
{"learn":[175.7035478],"iteration":418,"passed_time":0.2822803413,"remaining_time":0.3914197572},
{"learn":[175.138372],"iteration":419,"passed_time":0.2828839799,"remaining_time":0.3906493055},
{"learn":[174.4126757],"iteration":420,"passed_time":0.2834778887,"remaining_time":0.389866265},
{"learn":[173.8057866],"iteration":421,"passed_time":0.2841224879,"remaining_time":0.3891535498},
{"learn":[173.4298417],"iteration":422,"passed_time":0.2847398625,"remaining_time":0.3884040205},
{"learn":[173.0878973],"iteration":423,"passed_time":0.2854109116,"remaining_time":0.3877280308},
{"learn":[172.7348868],"iteration":424,"passed_time":0.2860745872,"remaining_time":0.3870420885},
{"learn":[172.5345495],"iteration":425,"passed_time":0.2868594535,"remaining_time":0.3865195453},
{"learn":[172.0105868],"iteration":426,"passed_time":0.287560147,"remaining_time":0.3858828202},
{"learn":[171.7336844],"iteration":427,"passed_time":0.2882157254,"remaining_time":0.3851855022},
{"learn":[170.5463951],"iteration":428,"passed_time":0.2887940435,"remaining_time":0.3843855451},
{"learn":[170.2107402],"iteration":429,"passed_time":0.2894441505,"remaining_time":0.3836817809},
{"learn":[169.2412333],"iteration":430,"passed_time":0.2901426488,"remaining_time":0.3830421512},
{"learn":[168.1901573],"iteration":431,"passed_time":0.2907913556,"remaining_time":0.3823367824},
{"learn":[167.7518282],"iteration":432,"passed_time":0.291546487,"remaining_time":0.3817710349},
{"learn":[167.320122],"iteration":433,"passed_time":0.2923165527,"remaining_time":0.3812238914},
{"learn":[166.7593872],"iteration":434,"passed_time":0.293020824,"remaining_time":0.3805902657},
{"learn":[166.1915862],"iteration":435,"passed_time":0.2936444298,"remaining_time":0.3798519689},
{"learn":[165.5028406],"iteration":436,"passed_time":0.2942054978,"remaining_time":0.3790336276},
{"learn":[164.8734838],"iteration":437,"passed_time":0.2948892107,"remaining_time":0.3783738274},
{"learn":[164.259899],"iteration":438,"passed_time":0.2955557256,"remaining_time":0.3776919409},
{"learn":[163.8498587],"iteration":439,"passed_time":0.296160192,"remaining_time":0.3769311535},
{"learn":[163.2377924],"iteration":440,"passed_time":0.2968241816,"remaining_time":0.376246525},
{"learn":[163.039982],"iteration":441,"passed_time":0.2974518795,"remaining_time":0.3755161736},
{"learn":[162.6648716],"iteration":442,"passed_time":0.298173018,"remaining_time":0.3749037721},
{"learn":[162.0847927],"iteration":443,"passed_time":0.2988862388,"remaining_time":0.3742809657},
{"learn":[161.1784426],"iteration":444,"passed_time":0.2995987619,"remaining_time":0.3736568828},
{"learn":[160.9295145],"iteration":445,"passed_time":0.3003244491,"remaining_time":0.3730487552},
{"learn":[160.7764534],"iteration":446,"passed_time":0.30094514,"remaining_time":0.3723102067},
{"learn":[160.1758901],"iteration":447,"passed_time":0.3016871377,"remaining_time":0.3717216518},
{"learn":[159.5974723],"iteration":448,"passed_time":0.3024234705,"remaining_time":0.3711254616},
{"learn":[158.9169409],"iteration":449,"passed_time":0.3030277039,"remaining_time":0.3703671936},
{"learn":[158.1264323],"iteration":450,"passed_time":0.3036426421,"remaining_time":0.3696226398},
{"learn":[157.9249254],"iteration":451,"passed_time":0.3043495468,"remaining_time":0.3689901585},
{"learn":[157.6240912],"iteration":452,"passed_time":0.3050685811,"remaining_time":0.3683719952},
{"learn":[156.9325219],"iteration":453,"passed_time":0.3059312817,"remaining_time":0.3679261669},
{"learn":[156.4621033],"iteration":454,"passed_time":0.306651503,"remaining_time":0.3673078443},
{"learn":[155.7456386],"iteration":455,"passed_time":0.3073148186,"remaining_time":0.3666211871},
{"learn":[155.5285567],"iteration":456,"passed_time":0.3079292118,"remaining_time":0.3658765033},
{"learn":[155.5071556],"iteration":457,"passed_time":0.308577597,"remaining_time":0.3651726147},
{"learn":[155.1443278],"iteration":458,"passed_time":0.3091677783,"remaining_time":0.3644003661},
{"learn":[154.7655873],"iteration":459,"passed_time":0.3097470936,"remaining_time":0.3636161534},
{"learn":[154.4996008],"iteration":460,"passed_time":0.3103618937,"remaining_time":0.3628743183},
{"learn":[154.0214905],"iteration":461,"passed_time":0.3109504798,"remaining_time":0.3621025068},
{"learn":[153.7131601],"iteration":462,"passed_time":0.3115729333,"remaining_time":0.3613707671},
{"learn":[153.5401138],"iteration":463,"passed_time":0.3121788792,"remaining_time":0.3606204295},
{"learn":[153.2052533],"iteration":464,"passed_time":0.3127517323,"remaining_time":0.3598326383},
{"learn":[152.7359408],"iteration":465,"passed_time":0.3133550052,"remaining_time":0.3590806283},
{"learn":[152.2995709],"iteration":466,"passed_time":0.3139249349,"remaining_time":0.3582911998},
{"learn":[151.9842201],"iteration":467,"passed_time":0.3144898582,"remaining_time":0.3574970183},
{"learn":[151.7254864],"iteration":468,"passed_time":0.3150743663,"remaining_time":0.3567259883},
{"learn":[151.2508952],"iteration":469,"passed_time":0.315661466,"remaining_time":0.3559586745},
{"learn":[150.5460567],"iteration":470,"passed_time":0.3162339082,"remaining_time":0.3551756633},
{"learn":[150.1308793],"iteration":471,"passed_time":0.3168121013,"remaining_time":0.3543999777},
{"learn":[149.8122492],"iteration":472,"passed_time":0.3174392368,"remaining_time":0.3536796571},
{"learn":[149.2563675],"iteration":473,"passed_time":0.3180598139,"remaining_time":0.3529524518},
{"learn":[148.7456909],"iteration":474,"passed_time":0.3186584048,"remaining_time":0.3522013948},
{"learn":[148.0807829],"iteration":475,"passed_time":0.3193259987,"remaining_time":0.3515269397},
{"learn":[147.5898177],"iteration":476,"passed_time":0.3200122124,"remaining_time":0.3508729289},
{"learn":[146.874288],"iteration":477,"passed_time":0.3207119227,"remaining_time":0.3502335222},
{"learn":[146.7153059],"iteration":478,"passed_time":0.3213732673,"remaining_time":0.3495521341},
{"learn":[146.6334919],"iteration":479,"passed_time":0.3219789961,"remaining_time":0.3488105792},
{"learn":[146.4810779],"iteration":480,"passed_time":0.3226653613,"remaining_time":0.3481565956},
{"learn":[146.1032451],"iteration":481,"passed_time":0.3232833423,"remaining_time":0.3474289861},
{"learn":[145.8308477],"iteration":482,"passed_time":0.3239009576,"remaining_time":0.346701439},
{"learn":[145.371106],"iteration":483,"passed_time":0.3246996969,"remaining_time":0.3461674454},
{"learn":[144.9808908],"iteration":484,"passed_time":0.3254278096,"remaining_time":0.3455573648},
{"learn":[144.6812394],"iteration":485,"passed_time":0.3261694793,"remaining_time":0.3449611365},
{"learn":[144.3134484],"iteration":486,"passed_time":0.3268967725,"remaining_time":0.344349167},
{"learn":[144.0248328],"iteration":487,"passed_time":0.3275185159,"remaining_time":0.3436259839},
{"learn":[143.6732554],"iteration":488,"passed_time":0.3282115072,"remaining_time":0.342977669},
{"learn":[143.517223],"iteration":489,"passed_time":0.3288481088,"remaining_time":0.3422704806},
{"learn":[143.0247819],"iteration":490,"passed_time":0.3294319224,"remaining_time":0.3415088564},
{"learn":[142.6108313],"iteration":491,"passed_time":0.3300855928,"remaining_time":0.3408200836},
{"learn":[142.3662203],"iteration":492,"passed_time":0.3307906527,"remaining_time":0.340184302},
{"learn":[141.8863868],"iteration":493,"passed_time":0.3315704897,"remaining_time":0.3396248336},
{"learn":[141.2083372],"iteration":494,"passed_time":0.3323149682,"remaining_time":0.3390284019},
{"learn":[140.7297502],"iteration":495,"passed_time":0.3329776442,"remaining_time":0.3383482513},
{"learn":[140.2895765],"iteration":496,"passed_time":0.3336637634,"remaining_time":0.3376918974},
{"learn":[139.7389128],"iteration":497,"passed_time":0.3343402378,"remaining_time":0.3370257016},
{"learn":[139.4452175],"iteration":498,"passed_time":0.335003915,"remaining_time":0.3363466161},
{"learn":[139.3039127],"iteration":499,"passed_time":0.335673976,"remaining_time":0.335673976},
{"learn":[138.8040046],"iteration":500,"passed_time":0.3363296174,"remaining_time":0.3349869842},
{"learn":[138.2129776],"iteration":501,"passed_time":0.3370412785,"remaining_time":0.3343556907},
{"learn":[137.7819186],"iteration":502,"passed_time":0.337724023,"remaining_time":0.3336955059},
{"learn":[137.7248519],"iteration":503,"passed_time":0.3384170707,"remaining_time":0.3330453712},
{"learn":[137.4418053],"iteration":504,"passed_time":0.3391681297,"remaining_time":0.3324519291},
{"learn":[137.0352111],"iteration":505,"passed_time":0.339836744,"remaining_time":0.3317773746},
{"learn":[136.528643],"iteration":506,"passed_time":0.340423261,"remaining_time":0.3310230132},
{"learn":[135.9824002],"iteration":507,"passed_time":0.3411246206,"remaining_time":0.3303805381},
{"learn":[135.9272128],"iteration":508,"passed_time":0.3417805214,"remaining_time":0.3296939804},
{"learn":[135.4505876],"iteration":509,"passed_time":0.3423754244,"remaining_time":0.3289489372},
{"learn":[134.8649302],"iteration":510,"passed_time":0.3430256087,"remaining_time":0.3282573829},
{"learn":[134.7185168],"iteration":511,"passed_time":0.3437491712,"remaining_time":0.3276359288},
{"learn":[134.6618628],"iteration":512,"passed_time":0.3445465652,"remaining_time":0.3270841662},
{"learn":[134.3109499],"iteration":513,"passed_time":0.3452623821,"remaining_time":0.3264543146},
{"learn":[134.1071167],"iteration":514,"passed_time":0.3458740173,"remaining_time":0.3257260163},
{"learn":[133.9162977],"iteration":515,"passed_time":0.3465056006,"remaining_time":0.3250168811},
{"learn":[133.8349891],"iteration":516,"passed_time":0.3471124076,"remaining_time":0.3242848992},
{"learn":[133.703733],"iteration":517,"passed_time":0.3478087916,"remaining_time":0.323636752},
{"learn":[133.3401595],"iteration":518,"passed_time":0.3484857899,"remaining_time":0.3229704527},
{"learn":[133.0947533],"iteration":519,"passed_time":0.3491812283,"remaining_time":0.3223211338},
{"learn":[132.7483724],"iteration":520,"passed_time":0.3498932563,"remaining_time":0.3216868902},
{"learn":[132.3012672],"iteration":521,"passed_time":0.350682306,"remaining_time":0.3211228779},
{"learn":[131.8710549],"iteration":522,"passed_time":0.3513713774,"remaining_time":0.3204668203},
{"learn":[131.6951105],"iteration":523,"passed_time":0.3519536422,"remaining_time":0.3197136139},
{"learn":[131.2545342],"iteration":524,"passed_time":0.3525500154,"remaining_time":0.3189738235},
{"learn":[130.6639752],"iteration":525,"passed_time":0.3531908281,"remaining_time":0.3182746246},
{"learn":[130.4218249],"iteration":526,"passed_time":0.3538755111,"remaining_time":0.3176150223},
{"learn":[130.1875315],"iteration":527,"passed_time":0.3545645136,"remaining_time":0.3169591864},
{"learn":[129.9272539],"iteration":528,"passed_time":0.3551467807,"remaining_time":0.3162081923},
{"learn":[129.5632709],"iteration":529,"passed_time":0.3557619221,"remaining_time":0.3154869875},
{"learn":[129.165251],"iteration":530,"passed_time":0.3564012548,"remaining_time":0.314787549},
{"learn":[128.3834328],"iteration":531,"passed_time":0.3570423571,"remaining_time":0.3140898931},
{"learn":[127.8802949],"iteration":532,"passed_time":0.3577706384,"remaining_time":0.3134688333},
{"learn":[127.8341099],"iteration":533,"passed_time":0.358360875,"remaining_time":0.3127269059},
{"learn":[127.7784739],"iteration":534,"passed_time":0.3589595604,"remaining_time":0.311992889},
{"learn":[127.6865117],"iteration":535,"passed_time":0.3596666449,"remaining_time":0.311353215},
{"learn":[127.3218478],"iteration":536,"passed_time":0.3603034981,"remaining_time":0.3106527367},
{"learn":[126.9320602],"iteration":537,"passed_time":0.3609049335,"remaining_time":0.3099220804},
{"learn":[126.8925047],"iteration":538,"passed_time":0.3614712281,"remaining_time":0.3091618482},
{"learn":[126.7094465],"iteration":539,"passed_time":0.3620447104,"remaining_time":0.308408457},
{"learn":[126.5601561],"iteration":540,"passed_time":0.3626148696,"remaining_time":0.3076529116},
{"learn":[126.2360248],"iteration":541,"passed_time":0.363242374,"remaining_time":0.3069465079},
{"learn":[125.3888709],"iteration":542,"passed_time":0.3638769527,"remaining_time":0.3062463488},
{"learn":[125.04148],"iteration":543,"passed_time":0.3645390327,"remaining_time":0.3055694833},
{"learn":[124.6847819],"iteration":544,"passed_time":0.3651632841,"remaining_time":0.3048610904},
{"learn":[124.2315076],"iteration":545,"passed_time":0.365768922,"remaining_time":0.3041375286},
{"learn":[124.142053],"iteration":546,"passed_time":0.3663289971,"remaining_time":0.3033766649},
{"learn":[123.6677454],"iteration":547,"passed_time":0.366916545,"remaining_time":0.3026391941},
{"learn":[123.5487394],"iteration":548,"passed_time":0.3674853782,"remaining_time":0.3018868954},
{"learn":[123.0825315],"iteration":549,"passed_time":0.3680757401,"remaining_time":0.3011528783},
{"learn":[122.8848238],"iteration":550,"passed_time":0.3689064693,"remaining_time":0.3006152535},
{"learn":[122.5239673],"iteration":551,"passed_time":0.3695973518,"remaining_time":0.2999630681},
{"learn":[122.2143782],"iteration":552,"passed_time":0.3702410121,"remaining_time":0.2992725722},
{"learn":[122.0287725],"iteration":553,"passed_time":0.3709480914,"remaining_time":0.298633301},
{"learn":[121.8526298],"iteration":554,"passed_time":0.3716108238,"remaining_time":0.2979582281},
{"learn":[121.4810839],"iteration":555,"passed_time":0.3722469621,"remaining_time":0.2972619626},
{"learn":[121.4465347],"iteration":556,"passed_time":0.3728804126,"remaining_time":0.2965637752},
{"learn":[121.002613],"iteration":557,"passed_time":0.3735265645,"remaining_time":0.2958758808},
{"learn":[120.7503577],"iteration":558,"passed_time":0.3741502764,"remaining_time":0.2951704327},
{"learn":[120.3465539],"iteration":559,"passed_time":0.3747814207,"remaining_time":0.2944711163},
{"learn":[120.1510024],"iteration":560,"passed_time":0.37546044,"remaining_time":0.2938095065},
{"learn":[119.7814409],"iteration":561,"passed_time":0.376155475,"remaining_time":0.2931603168},
{"learn":[119.7461596],"iteration":562,"passed_time":0.3767737981,"remaining_time":0.2924514205},
{"learn":[119.579444],"iteration":563,"passed_time":0.3773755286,"remaining_time":0.2917300186},
{"learn":[119.5413636],"iteration":564,"passed_time":0.3779600274,"remaining_time":0.2909957733},
{"learn":[119.230611],"iteration":565,"passed_time":0.3785684758,"remaining_time":0.2902804213},
{"learn":[119.1621474],"iteration":566,"passed_time":0.3791424018,"remaining_time":0.2895390829},
{"learn":[118.9014184],"iteration":567,"passed_time":0.3797199625,"remaining_time":0.2888010983},
{"learn":[118.8661866],"iteration":568,"passed_time":0.3802688653,"remaining_time":0.28804197},
{"learn":[118.4498577],"iteration":569,"passed_time":0.3808507615,"remaining_time":0.2873084692},
{"learn":[118.0449244],"iteration":570,"passed_time":0.3814713907,"remaining_time":0.2866046},
{"learn":[118.013937],"iteration":571,"passed_time":0.3821711851,"remaining_time":0.2859602574},
{"learn":[117.8156032],"iteration":572,"passed_time":0.3827878952,"remaining_time":0.2852538067},
{"learn":[117.7778827],"iteration":573,"passed_time":0.3834065835,"remaining_time":0.2845491369},
{"learn":[117.4409299],"iteration":574,"passed_time":0.3840532501,"remaining_time":0.2838654457},
{"learn":[117.2784949],"iteration":575,"passed_time":0.3846422174,"remaining_time":0.2831394101},
{"learn":[117.24783],"iteration":576,"passed_time":0.3852033503,"remaining_time":0.282393444},
{"learn":[117.0237875],"iteration":577,"passed_time":0.3857830125,"remaining_time":0.2816616458},
{"learn":[116.6116164],"iteration":578,"passed_time":0.3863667443,"remaining_time":0.2809333322},
{"learn":[116.3202336],"iteration":579,"passed_time":0.3869695823,"remaining_time":0.2802193527},
{"learn":[115.8512959],"iteration":580,"passed_time":0.3875922649,"remaining_time":0.2795200671},
{"learn":[115.688026],"iteration":581,"passed_time":0.3882072837,"remaining_time":0.2788155405},
{"learn":[115.6028459],"iteration":582,"passed_time":0.3888146242,"remaining_time":0.278105829},
{"learn":[115.3411921],"iteration":583,"passed_time":0.3894122619,"remaining_time":0.2773895564},
{"learn":[114.9109398],"iteration":584,"passed_time":0.3899775993,"remaining_time":0.2766507756},
{"learn":[114.4524579],"iteration":585,"passed_time":0.3905969941,"remaining_time":0.2759507774},
{"learn":[113.9154768],"iteration":586,"passed_time":0.391147128,"remaining_time":0.2752023235},
{"learn":[113.6797394],"iteration":587,"passed_time":0.3917107749,"remaining_time":0.2744640123},
{"learn":[113.4071217],"iteration":588,"passed_time":0.3922812701,"remaining_time":0.273731073},
{"learn":[113.0701311],"iteration":589,"passed_time":0.392870485,"remaining_time":0.273011693},
{"learn":[112.7114029],"iteration":590,"passed_time":0.3934520224,"remaining_time":0.2722874402},
{"learn":[112.5253886],"iteration":591,"passed_time":0.3940208063,"remaining_time":0.27155488},
{"learn":[112.1969816],"iteration":592,"passed_time":0.3946097239,"remaining_time":0.2708366908},
{"learn":[112.1519745],"iteration":593,"passed_time":0.395219069,"remaining_time":0.270132899},
{"learn":[111.8502601],"iteration":594,"passed_time":0.3958381687,"remaining_time":0.2694360644},
{"learn":[111.8199502],"iteration":595,"passed_time":0.3963871439,"remaining_time":0.2686919566},
{"learn":[111.7471483],"iteration":596,"passed_time":0.3969279562,"remaining_time":0.2679429922},
{"learn":[111.3626469],"iteration":597,"passed_time":0.397475446,"remaining_time":0.2671992128},
{"learn":[110.9521138],"iteration":598,"passed_time":0.398045332,"remaining_time":0.266471082},
{"learn":[110.5288464],"iteration":599,"passed_time":0.3986389141,"remaining_time":0.2657592761},
{"learn":[110.2251546],"iteration":600,"passed_time":0.3992036992,"remaining_time":0.2650287454},
{"learn":[109.9187882],"iteration":601,"passed_time":0.3997649442,"remaining_time":0.2642964249},
{"learn":[109.6911614],"iteration":602,"passed_time":0.4003161976,"remaining_time":0.2635580936},
{"learn":[109.323773],"iteration":603,"passed_time":0.400882948,"remaining_time":0.2628305421},
{"learn":[108.9373191],"iteration":604,"passed_time":0.4015155345,"remaining_time":0.262146506},
{"learn":[108.6527714],"iteration":605,"passed_time":0.4021376308,"remaining_time":0.2614558194},
{"learn":[108.3303839],"iteration":606,"passed_time":0.4027215,"remaining_time":0.2607406087},
{"learn":[108.1680462],"iteration":607,"passed_time":0.4032818494,"remaining_time":0.2600106661},
{"learn":[107.865723],"iteration":608,"passed_time":0.4038317783,"remaining_time":0.25927459},
{"learn":[107.4875713],"iteration":609,"passed_time":0.4044415391,"remaining_time":0.2585773775},
{"learn":[107.2306176],"iteration":610,"passed_time":0.4049866526,"remaining_time":0.2578392927},
{"learn":[106.7079548],"iteration":611,"passed_time":0.4055662735,"remaining_time":0.2571237159},
{"learn":[106.3074213],"iteration":612,"passed_time":0.4061391551,"remaining_time":0.2564043279},
{"learn":[105.9907428],"iteration":613,"passed_time":0.4067216413,"remaining_time":0.2556914553},
{"learn":[105.6779828],"iteration":614,"passed_time":0.4073056891,"remaining_time":0.2549799843},
{"learn":[105.6551256],"iteration":615,"passed_time":0.4078672137,"remaining_time":0.2542548864},
{"learn":[105.2926271],"iteration":616,"passed_time":0.408478754,"remaining_time":0.2535613659},
{"learn":[104.8866683],"iteration":617,"passed_time":0.4090482728,"remaining_time":0.2528421362},
{"learn":[104.6153194],"iteration":618,"passed_time":0.4096113914,"remaining_time":0.2521194509},
{"learn":[104.4263482],"iteration":619,"passed_time":0.4101713491,"remaining_time":0.251395343},
{"learn":[104.1537422],"iteration":620,"passed_time":0.4107287291,"remaining_time":0.2506701905},
{"learn":[104.1298282],"iteration":621,"passed_time":0.4112655379,"remaining_time":0.2499330761},
{"learn":[104.1072888],"iteration":622,"passed_time":0.4118211925,"remaining_time":0.249208009},
{"learn":[103.8978595],"iteration":623,"passed_time":0.412364778,"remaining_time":0.2484762124},
{"learn":[103.8057459],"iteration":624,"passed_time":0.4129052656,"remaining_time":0.2477431594},
{"learn":[103.7253774],"iteration":625,"passed_time":0.413465581,"remaining_time":0.2470225675},
{"learn":[103.5222677],"iteration":626,"passed_time":0.4140571072,"remaining_time":0.2463210542},
{"learn":[103.1131651],"iteration":627,"passed_time":0.414647234,"remaining_time":0.2456190622},
{"learn":[102.9775458],"iteration":628,"passed_time":0.4152080308,"remaining_time":0.2449001263},
{"learn":[102.8190196],"iteration":629,"passed_time":0.4157779886,"remaining_time":0.2441870727},
{"learn":[102.7982575],"iteration":630,"passed_time":0.4163471766,"remaining_time":0.2434740224},
{"learn":[102.1182996],"iteration":631,"passed_time":0.4169094417,"remaining_time":0.2427573964},
{"learn":[101.6770843],"iteration":632,"passed_time":0.4175039553,"remaining_time":0.2420599551},
{"learn":[101.527803],"iteration":633,"passed_time":0.4180821937,"remaining_time":0.2413534431},
{"learn":[101.1589857],"iteration":634,"passed_time":0.4187992827,"remaining_time":0.2407271467},
{"learn":[100.8425597],"iteration":635,"passed_time":0.4195500352,"remaining_time":0.2401198315},
{"learn":[100.5265852],"iteration":636,"passed_time":0.4202490678,"remaining_time":0.2394825928},
{"learn":[100.5046395],"iteration":637,"passed_time":0.4208653137,"remaining_time":0.2387981874},
{"learn":[100.1320677],"iteration":638,"passed_time":0.4215556864,"remaining_time":0.2381558729},
{"learn":[99.86063622],"iteration":639,"passed_time":0.4221372987,"remaining_time":0.2374522305},
{"learn":[99.66140117],"iteration":640,"passed_time":0.4227095486,"remaining_time":0.2367437254},
{"learn":[99.37021119],"iteration":641,"passed_time":0.4232862366,"remaining_time":0.2360381195},
{"learn":[99.35082368],"iteration":642,"passed_time":0.4238336703,"remaining_time":0.2353166723},
{"learn":[99.28925338],"iteration":643,"passed_time":0.4243829687,"remaining_time":0.2345967964},
{"learn":[99.0348],"iteration":644,"passed_time":0.4250202417,"remaining_time":0.2339258694},
{"learn":[98.73850345],"iteration":645,"passed_time":0.4256036959,"remaining_time":0.2332255547},
{"learn":[98.48125883],"iteration":646,"passed_time":0.4261787723,"remaining_time":0.2325210303},
{"learn":[98.25626368],"iteration":647,"passed_time":0.4267400461,"remaining_time":0.2318094077},
{"learn":[97.83505969],"iteration":648,"passed_time":0.4273210256,"remaining_time":0.231108906},
{"learn":[97.53467509],"iteration":649,"passed_time":0.4279102332,"remaining_time":0.2304132025},
{"learn":[97.40260771],"iteration":650,"passed_time":0.4284953993,"remaining_time":0.2297156595},
{"learn":[97.38273473],"iteration":651,"passed_time":0.4290765815,"remaining_time":0.2290163349},
{"learn":[97.09378938],"iteration":652,"passed_time":0.4296450794,"remaining_time":0.2283106318},
{"learn":[96.7559172],"iteration":653,"passed_time":0.4302231135,"remaining_time":0.2276103934},
{"learn":[96.44219582],"iteration":654,"passed_time":0.4308037005,"remaining_time":0.2269118728},
{"learn":[96.2273427],"iteration":655,"passed_time":0.4313803,"remaining_time":0.2262116207},
{"learn":[96.14107407],"iteration":656,"passed_time":0.4319600655,"remaining_time":0.225513398},
{"learn":[95.9990101],"iteration":657,"passed_time":0.4325511448,"remaining_time":0.2248214157},
{"learn":[95.94160715],"iteration":658,"passed_time":0.4331108874,"remaining_time":0.2241135244},
{"learn":[95.92343183],"iteration":659,"passed_time":0.433717962,"remaining_time":0.2234304653},
{"learn":[95.66032915],"iteration":660,"passed_time":0.4343235042,"remaining_time":0.2227468501},
{"learn":[95.39754584],"iteration":661,"passed_time":0.4348923846,"remaining_time":0.2220447523},
{"learn":[95.09130771],"iteration":662,"passed_time":0.4354596305,"remaining_time":0.2213422254},
{"learn":[94.93271899],"iteration":663,"passed_time":0.4360191544,"remaining_time":0.2206361986},
{"learn":[94.90891119],"iteration":664,"passed_time":0.4365991054,"remaining_time":0.2199409027},
{"learn":[94.74593834],"iteration":665,"passed_time":0.437189998,"remaining_time":0.2192514405},
{"learn":[94.4454494],"iteration":666,"passed_time":0.4377355509,"remaining_time":0.2185396378},
{"learn":[94.20140366],"iteration":667,"passed_time":0.4382821294,"remaining_time":0.2178288428},
{"learn":[93.98291281],"iteration":668,"passed_time":0.4388220639,"remaining_time":0.2171152513},
{"learn":[93.64969415],"iteration":669,"passed_time":0.4393655276,"remaining_time":0.2164039166},
{"learn":[93.26344398],"iteration":670,"passed_time":0.4399428833,"remaining_time":0.2157096998},
{"learn":[93.14435763],"iteration":671,"passed_time":0.4405026772,"remaining_time":0.2150072591},
{"learn":[93.12781378],"iteration":672,"passed_time":0.4410704057,"remaining_time":0.2143090976},
{"learn":[93.11149019],"iteration":673,"passed_time":0.4416327697,"remaining_time":0.2136087284},
{"learn":[93.10048054],"iteration":674,"passed_time":0.4421787243,"remaining_time":0.2129008672},
{"learn":[92.89167095],"iteration":675,"passed_time":0.4427228769,"remaining_time":0.2121926215},
{"learn":[92.55638263],"iteration":676,"passed_time":0.4432925823,"remaining_time":0.2114970518},
{"learn":[92.42850236],"iteration":677,"passed_time":0.4438342971,"remaining_time":0.21078856},
{"learn":[92.11976434],"iteration":678,"passed_time":0.444419339,"remaining_time":0.2101010424},
{"learn":[91.92332669],"iteration":679,"passed_time":0.4449671988,"remaining_time":0.2093963288},
{"learn":[91.89269964],"iteration":680,"passed_time":0.445537048,"remaining_time":0.2087023764},
{"learn":[91.5267367],"iteration":681,"passed_time":0.4461284457,"remaining_time":0.2080188354},
{"learn":[91.29183907],"iteration":682,"passed_time":0.4467352843,"remaining_time":0.2073427308},
{"learn":[91.11544539],"iteration":683,"passed_time":0.4473362543,"remaining_time":0.2066641175},
{"learn":[90.90387191],"iteration":684,"passed_time":0.4479390562,"remaining_time":0.2059865733},
{"learn":[90.89425768],"iteration":685,"passed_time":0.4485209957,"remaining_time":0.2052996978},
{"learn":[90.87931758],"iteration":686,"passed_time":0.4491218559,"remaining_time":0.204621748},
{"learn":[90.72260432],"iteration":687,"passed_time":0.449721638,"remaining_time":0.2039435335},
{"learn":[90.70729919],"iteration":688,"passed_time":0.4502953117,"remaining_time":0.2032537619},
{"learn":[90.69731477],"iteration":689,"passed_time":0.4508312874,"remaining_time":0.20254739},
{"learn":[90.49916704],"iteration":690,"passed_time":0.4514280316,"remaining_time":0.2018686856},
{"learn":[90.44526784],"iteration":691,"passed_time":0.4519934771,"remaining_time":0.2011762875},
{"learn":[90.14615629],"iteration":692,"passed_time":0.4525533916,"remaining_time":0.2004818055},
{"learn":[89.95829239],"iteration":693,"passed_time":0.4531713758,"remaining_time":0.1998133156},
{"learn":[89.79737641],"iteration":694,"passed_time":0.4537838157,"remaining_time":0.1991425378},
{"learn":[89.54261812],"iteration":695,"passed_time":0.4543964085,"remaining_time":0.1984719945},
{"learn":[89.53512199],"iteration":696,"passed_time":0.4550924557,"remaining_time":0.1978378968},
{"learn":[89.23283833],"iteration":697,"passed_time":0.4557438327,"remaining_time":0.1971842944},
{"learn":[88.96543296],"iteration":698,"passed_time":0.4563997171,"remaining_time":0.1965326393},
{"learn":[88.83367963],"iteration":699,"passed_time":0.4570453452,"remaining_time":0.1958765765},
{"learn":[88.71865941],"iteration":700,"passed_time":0.4577123567,"remaining_time":0.1952296643},
{"learn":[88.487805],"iteration":701,"passed_time":0.4583578486,"remaining_time":0.1945735596},
{"learn":[88.2632675],"iteration":702,"passed_time":0.4590893652,"remaining_time":0.1939538286},
{"learn":[88.13936073],"iteration":703,"passed_time":0.4598593172,"remaining_time":0.1933499402},
{"learn":[87.90477909],"iteration":704,"passed_time":0.4607962002,"remaining_time":0.1928154313},
{"learn":[87.62660584],"iteration":705,"passed_time":0.4616826609,"remaining_time":0.1922587851},
{"learn":[87.4703734],"iteration":706,"passed_time":0.4623305883,"remaining_time":0.1916023513},
{"learn":[87.20997145],"iteration":707,"passed_time":0.4629389934,"remaining_time":0.1909296413},
{"learn":[87.1065811],"iteration":708,"passed_time":0.4635277284,"remaining_time":0.1902490395},
{"learn":[87.09591869],"iteration":709,"passed_time":0.4640723757,"remaining_time":0.1895506887},
{"learn":[86.75085638],"iteration":710,"passed_time":0.4646369197,"remaining_time":0.1888608577},
{"learn":[86.61040964],"iteration":711,"passed_time":0.4651752501,"remaining_time":0.1881607753},
{"learn":[86.51425451],"iteration":712,"passed_time":0.4658322407,"remaining_time":0.1875089104},
{"learn":[86.42553375],"iteration":713,"passed_time":0.4666250505,"remaining_time":0.1869114348},
{"learn":[86.20975901],"iteration":714,"passed_time":0.4673256855,"remaining_time":0.1862766718},
{"learn":[86.02958216],"iteration":715,"passed_time":0.4679777134,"remaining_time":0.185622445},
{"learn":[85.88547252],"iteration":716,"passed_time":0.4687062322,"remaining_time":0.1849984152},
{"learn":[85.68449879],"iteration":717,"passed_time":0.469376137,"remaining_time":0.1843510733},
{"learn":[85.67210397],"iteration":718,"passed_time":0.4700802685,"remaining_time":0.1837170451},
{"learn":[85.38027166],"iteration":719,"passed_time":0.4709217251,"remaining_time":0.1831362264},
{"learn":[85.08785831],"iteration":720,"passed_time":0.4715781229,"remaining_time":0.1824830739},
{"learn":[84.85077355],"iteration":721,"passed_time":0.4722860133,"remaining_time":0.1818497392},
{"learn":[84.63381358],"iteration":722,"passed_time":0.4729695608,"remaining_time":0.1812068718},
{"learn":[84.477976],"iteration":723,"passed_time":0.4736360693,"remaining_time":0.1805573966},
{"learn":[84.14389324],"iteration":724,"passed_time":0.4743203024,"remaining_time":0.1799145975},
{"learn":[83.91596157],"iteration":725,"passed_time":0.4750111966,"remaining_time":0.1792741982},
{"learn":[83.57954875],"iteration":726,"passed_time":0.4756897493,"remaining_time":0.1786290255},
{"learn":[83.53690734],"iteration":727,"passed_time":0.4763898304,"remaining_time":0.1779918048},
{"learn":[83.25482477],"iteration":728,"passed_time":0.4770758847,"remaining_time":0.1773491972},
{"learn":[83.0617793],"iteration":729,"passed_time":0.4776981729,"remaining_time":0.1766828859},
{"learn":[82.97620757],"iteration":730,"passed_time":0.4783891527,"remaining_time":0.1760419727},
{"learn":[82.83495354],"iteration":731,"passed_time":0.4789918529,"remaining_time":0.1753686019},
{"learn":[82.58502882],"iteration":732,"passed_time":0.4795838453,"remaining_time":0.1746915235},
{"learn":[82.42368458],"iteration":733,"passed_time":0.4801401199,"remaining_time":0.1740017328},
{"learn":[82.11107845],"iteration":734,"passed_time":0.4807160998,"remaining_time":0.1733194101},
{"learn":[81.90779444],"iteration":735,"passed_time":0.4812736713,"remaining_time":0.1726307734},
{"learn":[81.69265935],"iteration":736,"passed_time":0.4818425352,"remaining_time":0.1719465221},
{"learn":[81.49811609],"iteration":737,"passed_time":0.4823973259,"remaining_time":0.1712575872},
{"learn":[81.35374164],"iteration":738,"passed_time":0.4829753708,"remaining_time":0.1705772284},
{"learn":[81.27684655],"iteration":739,"passed_time":0.4835534831,"remaining_time":0.1698971697},
{"learn":[81.22059389],"iteration":740,"passed_time":0.4841208447,"remaining_time":0.1692136286},
{"learn":[81.00525704],"iteration":741,"passed_time":0.4847096919,"remaining_time":0.1685378713},
{"learn":[80.76784331],"iteration":742,"passed_time":0.4853004992,"remaining_time":0.167863026},
{"learn":[80.53642725],"iteration":743,"passed_time":0.4858964731,"remaining_time":0.1671901843},
{"learn":[80.52809031],"iteration":744,"passed_time":0.4864463688,"remaining_time":0.1665017772},
{"learn":[80.24737763],"iteration":745,"passed_time":0.4870222609,"remaining_time":0.1658225929},
{"learn":[80.23944575],"iteration":746,"passed_time":0.4875643373,"remaining_time":0.165132232},
{"learn":[80.09333241],"iteration":747,"passed_time":0.488105724,"remaining_time":0.1644420354},
{"learn":[79.90613521],"iteration":748,"passed_time":0.4887008721,"remaining_time":0.1637702522},
{"learn":[79.81809626],"iteration":749,"passed_time":0.489309942,"remaining_time":0.163103314},
{"learn":[79.61451384],"iteration":750,"passed_time":0.4899040031,"remaining_time":0.1624315536},
{"learn":[79.55760304],"iteration":751,"passed_time":0.490288929,"remaining_time":0.1616910298},
{"learn":[79.41771871],"iteration":752,"passed_time":0.4908855082,"remaining_time":0.1610208772},
{"learn":[79.33459938],"iteration":753,"passed_time":0.4915033858,"remaining_time":0.1603578686},
{"learn":[79.32387204],"iteration":754,"passed_time":0.4921205125,"remaining_time":0.1596947358},
{"learn":[79.06232166],"iteration":755,"passed_time":0.4927457087,"remaining_time":0.1590343293},
{"learn":[78.97354017],"iteration":756,"passed_time":0.4933365417,"remaining_time":0.158362985},
{"learn":[78.90631069],"iteration":757,"passed_time":0.4939142598,"remaining_time":0.1576876661},
{"learn":[78.89891093],"iteration":758,"passed_time":0.4944767588,"remaining_time":0.1570077719},
{"learn":[78.84541583],"iteration":759,"passed_time":0.4950699852,"remaining_time":0.1563378901},
{"learn":[78.68558956],"iteration":760,"passed_time":0.4956813389,"remaining_time":0.1556739027},
{"learn":[78.59860918],"iteration":761,"passed_time":0.496265736,"remaining_time":0.1550016341},
{"learn":[78.42847537],"iteration":762,"passed_time":0.4968395667,"remaining_time":0.1543263136},
{"learn":[78.28419025],"iteration":763,"passed_time":0.4973818237,"remaining_time":0.1536415057},
{"learn":[77.94836203],"iteration":764,"passed_time":0.4981058756,"remaining_time":0.153012916},
{"learn":[77.77257736],"iteration":765,"passed_time":0.498792654,"remaining_time":0.1523726907},
{"learn":[77.53200536],"iteration":766,"passed_time":0.4994715416,"remaining_time":0.1517299468},
{"learn":[77.40969669],"iteration":767,"passed_time":0.5001859463,"remaining_time":0.1510978379},
{"learn":[77.26463767],"iteration":768,"passed_time":0.5008039128,"remaining_time":0.150436546},
{"learn":[77.06471213],"iteration":769,"passed_time":0.5014054059,"remaining_time":0.1497704459},
{"learn":[76.97560567],"iteration":770,"passed_time":0.5019858387,"remaining_time":0.1490982582},
{"learn":[76.89838105],"iteration":771,"passed_time":0.5025436873,"remaining_time":0.1484196382},
{"learn":[76.73794534],"iteration":772,"passed_time":0.5031347373,"remaining_time":0.1477510807},
{"learn":[76.53061777],"iteration":773,"passed_time":0.5038009097,"remaining_time":0.1471046584},
{"learn":[76.38653742],"iteration":774,"passed_time":0.5045599185,"remaining_time":0.1464851376},
{"learn":[76.27787759],"iteration":775,"passed_time":0.5052605988,"remaining_time":0.1458484203},
{"learn":[76.2087956],"iteration":776,"passed_time":0.5059310307,"remaining_time":0.1452028569},
{"learn":[76.00919882],"iteration":777,"passed_time":0.5065529403,"remaining_time":0.144543384},
{"learn":[75.91970864],"iteration":778,"passed_time":0.5071084231,"remaining_time":0.1438651624},
{"learn":[75.90907615],"iteration":779,"passed_time":0.5073932221,"remaining_time":0.1431109088},
{"learn":[75.83476363],"iteration":780,"passed_time":0.5079527164,"remaining_time":0.1424348846},
{"learn":[75.82725753],"iteration":781,"passed_time":0.5084950403,"remaining_time":0.1417543719},
{"learn":[75.82126107],"iteration":782,"passed_time":0.5090369982,"remaining_time":0.1410741106},
{"learn":[75.53296432],"iteration":783,"passed_time":0.509605291,"remaining_time":0.1404014577},
{"learn":[75.52109372],"iteration":784,"passed_time":0.5101459515,"remaining_time":0.1397215027},
{"learn":[75.39649449],"iteration":785,"passed_time":0.5108784379,"remaining_time":0.1390941294},
{"learn":[75.37741233],"iteration":786,"passed_time":0.5116043646,"remaining_time":0.1384647137},
{"learn":[75.15875347],"iteration":787,"passed_time":0.5122862704,"remaining_time":0.1378232098},
{"learn":[74.99782148],"iteration":788,"passed_time":0.5129954796,"remaining_time":0.1371889052},
{"learn":[74.86535342],"iteration":789,"passed_time":0.5136937072,"remaining_time":0.1365514918},
{"learn":[74.85872122],"iteration":790,"passed_time":0.5143670912,"remaining_time":0.1359073604},
{"learn":[74.5906124],"iteration":791,"passed_time":0.5150521347,"remaining_time":0.1352662172},
{"learn":[74.43114304],"iteration":792,"passed_time":0.5158019416,"remaining_time":0.1346418687},
{"learn":[74.19831702],"iteration":793,"passed_time":0.516466087,"remaining_time":0.1339949798},
{"learn":[73.97170788],"iteration":794,"passed_time":0.5171609278,"remaining_time":0.1333559625},
{"learn":[73.89262616],"iteration":795,"passed_time":0.5178802853,"remaining_time":0.1327230882},
{"learn":[73.78842022],"iteration":796,"passed_time":0.5185827282,"remaining_time":0.1320856886},
{"learn":[73.48422514],"iteration":797,"passed_time":0.5192533235,"remaining_time":0.1314400644},
{"learn":[73.20428317],"iteration":798,"passed_time":0.5199521535,"remaining_time":0.1308014804},
{"learn":[73.19916742],"iteration":799,"passed_time":0.5206612554,"remaining_time":0.1301653138},
{"learn":[72.8099612],"iteration":800,"passed_time":0.5212928522,"remaining_time":0.1295097099},
{"learn":[72.79918155],"iteration":801,"passed_time":0.5219362246,"remaining_time":0.1288570729},
{"learn":[72.68140778],"iteration":802,"passed_time":0.5226194613,"remaining_time":0.1282142389},
{"learn":[72.4717959],"iteration":803,"passed_time":0.523325742,"remaining_time":0.1275769222},
{"learn":[72.4585716],"iteration":804,"passed_time":0.5239753487,"remaining_time":0.1269257056},
{"learn":[72.20026565],"iteration":805,"passed_time":0.5246483663,"remaining_time":0.1262801279},
{"learn":[71.78456142],"iteration":806,"passed_time":0.5253937949,"remaining_time":0.1256517998},
{"learn":[71.63638527],"iteration":807,"passed_time":0.5260719527,"remaining_time":0.1250071967},
{"learn":[71.53057008],"iteration":808,"passed_time":0.5267131326,"remaining_time":0.1243537804},
{"learn":[71.40533479],"iteration":809,"passed_time":0.5273983695,"remaining_time":0.1237107286},
{"learn":[71.27356013],"iteration":810,"passed_time":0.528074872,"remaining_time":0.1230655374},
{"learn":[71.05413259],"iteration":811,"passed_time":0.5287418554,"remaining_time":0.122418065},
{"learn":[70.87869771],"iteration":812,"passed_time":0.5293949254,"remaining_time":0.1217673445},
{"learn":[70.75088378],"iteration":813,"passed_time":0.5300195333,"remaining_time":0.1211101145},
{"learn":[70.44463871],"iteration":814,"passed_time":0.5307002628,"remaining_time":0.1204657038},
{"learn":[70.34790421],"iteration":815,"passed_time":0.5313975848,"remaining_time":0.1198249456},
{"learn":[70.22087424],"iteration":816,"passed_time":0.5321052605,"remaining_time":0.119186368},
{"learn":[70.11268784],"iteration":817,"passed_time":0.5328077162,"remaining_time":0.1185464601},
{"learn":[70.0684417],"iteration":818,"passed_time":0.5335004852,"remaining_time":0.1179042586},
{"learn":[69.91418852],"iteration":819,"passed_time":0.53417945,"remaining_time":0.1172589037},
{"learn":[69.61552602],"iteration":820,"passed_time":0.5348660975,"remaining_time":0.1166151418},
{"learn":[69.35610062],"iteration":821,"passed_time":0.5355743539,"remaining_time":0.115975955},
{"learn":[69.35159583],"iteration":822,"passed_time":0.5362556698,"remaining_time":0.1153308063},
{"learn":[69.34682836],"iteration":823,"passed_time":0.5369136633,"remaining_time":0.1146805883},
{"learn":[69.19517397],"iteration":824,"passed_time":0.5376464768,"remaining_time":0.1140462224},
{"learn":[69.02633339],"iteration":825,"passed_time":0.5383315559,"remaining_time":0.1134015626},
{"learn":[68.93174154],"iteration":826,"passed_time":0.5390559863,"remaining_time":0.112765037},
{"learn":[68.63331086],"iteration":827,"passed_time":0.5398228271,"remaining_time":0.112137109},
{"learn":[68.54095959],"iteration":828,"passed_time":0.540491568,"remaining_time":0.1114886105},
{"learn":[68.31808371],"iteration":829,"passed_time":0.5411169196,"remaining_time":0.1108311763},
{"learn":[68.12550858],"iteration":830,"passed_time":0.5417618804,"remaining_time":0.1101778072},
{"learn":[68.05351749],"iteration":831,"passed_time":0.5424775912,"remaining_time":0.1095387444},
{"learn":[67.97895887],"iteration":832,"passed_time":0.5431430711,"remaining_time":0.1088894272},
{"learn":[67.83798036],"iteration":833,"passed_time":0.5438272238,"remaining_time":0.108243788},
{"learn":[67.63365994],"iteration":834,"passed_time":0.5444937235,"remaining_time":0.1075945681},
{"learn":[67.53561524],"iteration":835,"passed_time":0.5451389206,"remaining_time":0.106941128},
{"learn":[67.22466174],"iteration":836,"passed_time":0.5458131882,"remaining_time":0.1062933688},
{"learn":[66.99431593],"iteration":837,"passed_time":0.5464644038,"remaining_time":0.10564109},
{"learn":[66.80247672],"iteration":838,"passed_time":0.5471362459,"remaining_time":0.1049927719},
{"learn":[66.63658737],"iteration":839,"passed_time":0.547913025,"remaining_time":0.1043643857},
{"learn":[66.50986653],"iteration":840,"passed_time":0.5485903245,"remaining_time":0.103716839},
{"learn":[66.4117221],"iteration":841,"passed_time":0.5492282191,"remaining_time":0.1030618273},
{"learn":[66.19505087],"iteration":842,"passed_time":0.5500057003,"remaining_time":0.1024328528},
{"learn":[66.18944688],"iteration":843,"passed_time":0.5507998886,"remaining_time":0.1018066145},
{"learn":[66.00274214],"iteration":844,"passed_time":0.5515345934,"remaining_time":0.1011690674},
{"learn":[65.80389279],"iteration":845,"passed_time":0.5522515437,"remaining_time":0.1005280588},
{"learn":[65.73348199],"iteration":846,"passed_time":0.5529318363,"remaining_time":0.09988024906},
{"learn":[65.51365456],"iteration":847,"passed_time":0.5536137645,"remaining_time":0.0992326559},
{"learn":[65.42814403],"iteration":848,"passed_time":0.5543648595,"remaining_time":0.09859728361},
{"learn":[65.26690967],"iteration":849,"passed_time":0.5551408957,"remaining_time":0.09796604042},
{"learn":[65.16782435],"iteration":850,"passed_time":0.5557761793,"remaining_time":0.09730981282},
{"learn":[64.97000786],"iteration":851,"passed_time":0.5564699932,"remaining_time":0.09666380163},
{"learn":[64.87844538],"iteration":852,"passed_time":0.5568777324,"remaining_time":0.09596837826},
{"learn":[64.83721521],"iteration":853,"passed_time":0.557569768,"remaining_time":0.095322232},
{"learn":[64.78036485],"iteration":854,"passed_time":0.5583183622,"remaining_time":0.09468557019},
{"learn":[64.60058335],"iteration":855,"passed_time":0.5590105423,"remaining_time":0.09403915666},
{"learn":[64.37716818],"iteration":856,"passed_time":0.5597141832,"remaining_time":0.09339454866},
{"learn":[64.26365371],"iteration":857,"passed_time":0.5603426132,"remaining_time":0.09273735557},
{"learn":[64.18451689],"iteration":858,"passed_time":0.5610028797,"remaining_time":0.09208545522},
{"learn":[64.01978405],"iteration":859,"passed_time":0.5617427823,"remaining_time":0.09144649944},
{"learn":[63.80399033],"iteration":860,"passed_time":0.562472443,"remaining_time":0.09080565572},
{"learn":[63.62227497],"iteration":861,"passed_time":0.5631640845,"remaining_time":0.09015851933},
{"learn":[63.44441795],"iteration":862,"passed_time":0.5638292905,"remaining_time":0.08950708319},
{"learn":[63.33431937],"iteration":863,"passed_time":0.5645957171,"remaining_time":0.08887154807},
{"learn":[63.18641175],"iteration":864,"passed_time":0.5654840162,"remaining_time":0.08825473085},
{"learn":[63.07151833],"iteration":865,"passed_time":0.5661992968,"remaining_time":0.08761051475},
{"learn":[62.83553587],"iteration":866,"passed_time":0.5669794719,"remaining_time":0.08697608969},
{"learn":[62.64517657],"iteration":867,"passed_time":0.5676514502,"remaining_time":0.08632487491},
{"learn":[62.46638638],"iteration":868,"passed_time":0.5683308808,"remaining_time":0.08567473577},
{"learn":[62.46108967],"iteration":869,"passed_time":0.5690954691,"remaining_time":0.085037254},
{"learn":[62.42005848],"iteration":870,"passed_time":0.5697486096,"remaining_time":0.08438297433},
{"learn":[62.34527891],"iteration":871,"passed_time":0.5705171253,"remaining_time":0.08374563308},
{"learn":[62.19638256],"iteration":872,"passed_time":0.5711708129,"remaining_time":0.08309128665},
{"learn":[62.10815093],"iteration":873,"passed_time":0.5718857195,"remaining_time":0.08244576734},
{"learn":[61.96232056],"iteration":874,"passed_time":0.5726022093,"remaining_time":0.08180031561},
{"learn":[61.76312238],"iteration":875,"passed_time":0.5732111054,"remaining_time":0.08113947154},
{"learn":[61.69173957],"iteration":876,"passed_time":0.5738326646,"remaining_time":0.08048052194},
{"learn":[61.65039311],"iteration":877,"passed_time":0.5745995146,"remaining_time":0.07984184599},
{"learn":[61.52254915],"iteration":878,"passed_time":0.5752888824,"remaining_time":0.07919221248},
{"learn":[61.37684507],"iteration":879,"passed_time":0.5760645813,"remaining_time":0.07855426109},
{"learn":[61.24402025],"iteration":880,"passed_time":0.5767456336,"remaining_time":0.07790321272},
{"learn":[61.20094547],"iteration":881,"passed_time":0.5774001463,"remaining_time":0.07724854565},
{"learn":[60.95345394],"iteration":882,"passed_time":0.5781083975,"remaining_time":0.07660099944},
{"learn":[60.89399222],"iteration":883,"passed_time":0.5788880435,"remaining_time":0.07596268444},
{"learn":[60.75292351],"iteration":884,"passed_time":0.5794694564,"remaining_time":0.07529829094},
{"learn":[60.41323629],"iteration":885,"passed_time":0.5800575622,"remaining_time":0.07463494593},
{"learn":[60.36914331],"iteration":886,"passed_time":0.5807195817,"remaining_time":0.07398118685},
{"learn":[60.21158189],"iteration":887,"passed_time":0.5815011013,"remaining_time":0.07334248125},
{"learn":[60.10314949],"iteration":888,"passed_time":0.5821713045,"remaining_time":0.07268955546},
{"learn":[59.97908951],"iteration":889,"passed_time":0.5828301051,"remaining_time":0.07203518153},
{"learn":[59.84748721],"iteration":890,"passed_time":0.5835085152,"remaining_time":0.07138319659},
{"learn":[59.74426695],"iteration":891,"passed_time":0.5842350855,"remaining_time":0.07073698345},
{"learn":[59.64254717],"iteration":892,"passed_time":0.5848959856,"remaining_time":0.07008272168},
{"learn":[59.48614976],"iteration":893,"passed_time":0.5855836276,"remaining_time":0.0694316158},
{"learn":[59.37877471],"iteration":894,"passed_time":0.5862518626,"remaining_time":0.06877815148},
{"learn":[59.23263454],"iteration":895,"passed_time":0.5869286463,"remaining_time":0.06812564644},
{"learn":[59.02058358],"iteration":896,"passed_time":0.587583843,"remaining_time":0.0674706085},
{"learn":[58.9996374],"iteration":897,"passed_time":0.5879106063,"remaining_time":0.06677826486},
{"learn":[58.91265299],"iteration":898,"passed_time":0.5886514433,"remaining_time":0.06613325448},
{"learn":[58.72137119],"iteration":899,"passed_time":0.5894123104,"remaining_time":0.06549025672},
{"learn":[58.34422836],"iteration":900,"passed_time":0.5902020642,"remaining_time":0.06485017132},
{"learn":[58.19833006],"iteration":901,"passed_time":0.59087179,"remaining_time":0.06419671333},
{"learn":[57.9476249],"iteration":902,"passed_time":0.5915952487,"remaining_time":0.06354899128},
{"learn":[57.86466128],"iteration":903,"passed_time":0.5922925086,"remaining_time":0.0628983195},
{"learn":[57.76455175],"iteration":904,"passed_time":0.5929588705,"remaining_time":0.06224430132},
{"learn":[57.55439045],"iteration":905,"passed_time":0.5936825892,"remaining_time":0.06159620682},
{"learn":[57.46584223],"iteration":906,"passed_time":0.5944045295,"remaining_time":0.06094776323},
{"learn":[57.18340472],"iteration":907,"passed_time":0.5951591282,"remaining_time":0.06030246674},
{"learn":[57.15059287],"iteration":908,"passed_time":0.5959191278,"remaining_time":0.05965747044},
{"learn":[57.04548562],"iteration":909,"passed_time":0.596575299,"remaining_time":0.05900195265},
{"learn":[56.87282985],"iteration":910,"passed_time":0.5972549491,"remaining_time":0.05834872719},
{"learn":[56.77778327],"iteration":911,"passed_time":0.5979945314,"remaining_time":0.05770122671},
{"learn":[56.66448757],"iteration":912,"passed_time":0.5986553081,"remaining_time":0.05704601512},
{"learn":[56.57738916],"iteration":913,"passed_time":0.5993378851,"remaining_time":0.05639284258},
{"learn":[56.44039517],"iteration":914,"passed_time":0.5999969949,"remaining_time":0.05573742575},
{"learn":[56.3043867],"iteration":915,"passed_time":0.6007096205,"remaining_time":0.05508690843},
{"learn":[56.21818037],"iteration":916,"passed_time":0.6013673657,"remaining_time":0.05443128828},
{"learn":[56.11695499],"iteration":917,"passed_time":0.6020947803,"remaining_time":0.05378188669},
{"learn":[56.01130438],"iteration":918,"passed_time":0.6028225245,"remaining_time":0.05313234438},
{"learn":[55.97210669],"iteration":919,"passed_time":0.6035179481,"remaining_time":0.05247982157},
{"learn":[55.92444982],"iteration":920,"passed_time":0.6041710682,"remaining_time":0.05182357697},
{"learn":[55.8439695],"iteration":921,"passed_time":0.6049052675,"remaining_time":0.05117419833},
{"learn":[55.79011148],"iteration":922,"passed_time":0.6055934738,"remaining_time":0.050520799},
{"learn":[55.72826365],"iteration":923,"passed_time":0.6062879761,"remaining_time":0.04986784219},
{"learn":[55.68634115],"iteration":924,"passed_time":0.6070542923,"remaining_time":0.04922061829},
{"learn":[55.58759395],"iteration":925,"passed_time":0.6077674361,"remaining_time":0.04856888799},
{"learn":[55.49154761],"iteration":926,"passed_time":0.6085518583,"remaining_time":0.04792263825},
{"learn":[55.40218502],"iteration":927,"passed_time":0.6093384548,"remaining_time":0.04727625943},
{"learn":[55.26077416],"iteration":928,"passed_time":0.6100509823,"remaining_time":0.04662391792},
{"learn":[55.01071962],"iteration":929,"passed_time":0.6107650999,"remaining_time":0.04597156666},
{"learn":[54.9702762],"iteration":930,"passed_time":0.6114814239,"remaining_time":0.04531924624},
{"learn":[54.85957868],"iteration":931,"passed_time":0.6122155318,"remaining_time":0.04466808601},
{"learn":[54.78682478],"iteration":932,"passed_time":0.6129402306,"remaining_time":0.04401607229},
{"learn":[54.60376344],"iteration":933,"passed_time":0.6136836481,"remaining_time":0.04336522567},
{"learn":[54.56775391],"iteration":934,"passed_time":0.6145085838,"remaining_time":0.04271984807},
{"learn":[54.35979552],"iteration":935,"passed_time":0.6152729987,"remaining_time":0.04206994863},
{"learn":[54.25367891],"iteration":936,"passed_time":0.6159847064,"remaining_time":0.04141626094},
{"learn":[54.22769327],"iteration":937,"passed_time":0.6166953859,"remaining_time":0.04076238158},
{"learn":[54.05328063],"iteration":938,"passed_time":0.617421341,"remaining_time":0.04010937359},
{"learn":[53.88016438],"iteration":939,"passed_time":0.6181510486,"remaining_time":0.03945644991},
{"learn":[53.8017661],"iteration":940,"passed_time":0.6189126835,"remaining_time":0.03880536485},
{"learn":[53.79688349],"iteration":941,"passed_time":0.6196608083,"remaining_time":0.03815321325},
{"learn":[53.73644675],"iteration":942,"passed_time":0.6203166098,"remaining_time":0.03749527758},
{"learn":[53.57982669],"iteration":943,"passed_time":0.621057478,"remaining_time":0.03684239277},
{"learn":[53.42160773],"iteration":944,"passed_time":0.62171209,"remaining_time":0.03618430154},
{"learn":[53.32367442],"iteration":945,"passed_time":0.6223843094,"remaining_time":0.03552722274},
{"learn":[53.14198951],"iteration":946,"passed_time":0.6230804339,"remaining_time":0.03487144984},
{"learn":[53.06574847],"iteration":947,"passed_time":0.6237855723,"remaining_time":0.03421608624},
{"learn":[53.06082164],"iteration":948,"passed_time":0.624574469,"remaining_time":0.03356511899},
{"learn":[53.04785602],"iteration":949,"passed_time":0.6252707945,"remaining_time":0.03290898918},
{"learn":[52.98352617],"iteration":950,"passed_time":0.6259340944,"remaining_time":0.03225107321},
{"learn":[52.97931765],"iteration":951,"passed_time":0.6266269979,"remaining_time":0.03159463855},
{"learn":[52.90860299],"iteration":952,"passed_time":0.627305841,"remaining_time":0.03093743392},
{"learn":[52.76776105],"iteration":953,"passed_time":0.6279851843,"remaining_time":0.03028020805},
{"learn":[52.72990418],"iteration":954,"passed_time":0.6286264352,"remaining_time":0.02962114092},
{"learn":[52.57841655],"iteration":955,"passed_time":0.629338456,"remaining_time":0.02896536827},
{"learn":[52.44134716],"iteration":956,"passed_time":0.6300590427,"remaining_time":0.02830986294},
{"learn":[52.29582288],"iteration":957,"passed_time":0.6306910144,"remaining_time":0.02765033675},
{"learn":[52.22554872],"iteration":958,"passed_time":0.6313580763,"remaining_time":0.02699236823},
{"learn":[52.06780587],"iteration":959,"passed_time":0.6320649794,"remaining_time":0.02633604081},
{"learn":[51.91318998],"iteration":960,"passed_time":0.6328112414,"remaining_time":0.02568120543},
{"learn":[51.78720537],"iteration":961,"passed_time":0.6336148674,"remaining_time":0.02502844591},
{"learn":[51.69863524],"iteration":962,"passed_time":0.6344014832,"remaining_time":0.0243747195},
{"learn":[51.54479355],"iteration":963,"passed_time":0.6351719334,"remaining_time":0.0237201137},
{"learn":[51.45899],"iteration":964,"passed_time":0.6358730615,"remaining_time":0.02306275353},
{"learn":[51.38020568],"iteration":965,"passed_time":0.6365456437,"remaining_time":0.02240429802},
{"learn":[51.19951905],"iteration":966,"passed_time":0.6372761563,"remaining_time":0.02174779024},
{"learn":[51.12879154],"iteration":967,"passed_time":0.6379136503,"remaining_time":0.02108805456},
{"learn":[51.08390274],"iteration":968,"passed_time":0.6386115971,"remaining_time":0.02043029877},
{"learn":[50.93798203],"iteration":969,"passed_time":0.6393342055,"remaining_time":0.01977322285},
{"learn":[50.7620993],"iteration":970,"passed_time":0.640067768,"remaining_time":0.01911633911},
{"learn":[50.71587223],"iteration":971,"passed_time":0.6407448825,"remaining_time":0.01845767151},
{"learn":[50.6057186],"iteration":972,"passed_time":0.6414433792,"remaining_time":0.01779955934},
{"learn":[50.57816307],"iteration":973,"passed_time":0.6421165282,"remaining_time":0.01714068761},
{"learn":[50.54797058],"iteration":974,"passed_time":0.6428375418,"remaining_time":0.01648301389},
{"learn":[50.45765604],"iteration":975,"passed_time":0.6434420034,"remaining_time":0.01582234435},
{"learn":[50.40199271],"iteration":976,"passed_time":0.644072488,"remaining_time":0.01516240248},
{"learn":[50.30085862],"iteration":977,"passed_time":0.6447641515,"remaining_time":0.01450389707},
{"learn":[50.19669637],"iteration":978,"passed_time":0.6454594509,"remaining_time":0.01384540191},
{"learn":[50.06145739],"iteration":979,"passed_time":0.6461531431,"remaining_time":0.01318679884},
{"learn":[49.87767936],"iteration":980,"passed_time":0.6468421604,"remaining_time":0.01252803369},
{"learn":[49.85241291],"iteration":981,"passed_time":0.64752362,"remaining_time":0.01186906839},
{"learn":[49.77210496],"iteration":982,"passed_time":0.6482070161,"remaining_time":0.01121009082},
{"learn":[49.67467959],"iteration":983,"passed_time":0.6488745992,"remaining_time":0.01055080649},
{"learn":[49.25948908],"iteration":984,"passed_time":0.6495356791,"remaining_time":0.00989140628},
{"learn":[49.12515937],"iteration":985,"passed_time":0.6502204349,"remaining_time":0.009232338833},
{"learn":[48.97322741],"iteration":986,"passed_time":0.6509218333,"remaining_time":0.008573438534},
{"learn":[48.9263969],"iteration":987,"passed_time":0.6516198955,"remaining_time":0.007914411686},
{"learn":[48.76541074],"iteration":988,"passed_time":0.6523828056,"remaining_time":0.007256027161},
{"learn":[48.61949906],"iteration":989,"passed_time":0.6530653943,"remaining_time":0.006596620145},
{"learn":[48.61281748],"iteration":990,"passed_time":0.6537278179,"remaining_time":0.00593698321},
{"learn":[48.57655327],"iteration":991,"passed_time":0.6543594889,"remaining_time":0.005277092652},
{"learn":[48.49544013],"iteration":992,"passed_time":0.6550783733,"remaining_time":0.004617873729},
{"learn":[48.47246262],"iteration":993,"passed_time":0.6557576678,"remaining_time":0.003958295781},
{"learn":[48.45781735],"iteration":994,"passed_time":0.6564185566,"remaining_time":0.003298585712},
{"learn":[48.41794998],"iteration":995,"passed_time":0.6570990066,"remaining_time":0.002638951834},
{"learn":[48.34233226],"iteration":996,"passed_time":0.657769434,"remaining_time":0.00197924604},
{"learn":[48.31021723],"iteration":997,"passed_time":0.6584472326,"remaining_time":0.001319533532},
{"learn":[48.2365113],"iteration":998,"passed_time":0.6590754615,"remaining_time":0.0006597351967},
{"learn":[48.0939311],"iteration":999,"passed_time":0.6597757994,"remaining_time":0}
]}